Aliens/verilog/PAL16L8_053326_D21.v
//PAL16L8_053326_D21.v
//Implementation of PAL 053326-D21 combinatorial logic
//used in Aliens Konami Arcade PCB.
//Converted to Verilog By RndMnkIII. 10/2019. (@RndMnkIII).
//---------------------------------------------------------
//Dumped from an unsecured PAL16L8, 
//converted to GAL16V8 with PALTOGAL 
//and tested by Caius (@Caius63417737).
//---------------------------------------------------------
`timescale 1ns / 1ns
module PAL16L8_053326_D21(in, out);
	input [9:0] in;
	//wire [9:0] in;
	output [7:0] out;
	
	assign #5 out[0] =  ~(~in[3] & ~in[4] & ~in[5] & ~in[6] & ~in[7] & ~in[8] & in[9]);
	
	assign #5 out[1] =  ~((~in[0] & ~in[3] & ~in[4] & ~in[5] & ~in[6] & ~in[7] & in[8]) |
       (~in[0] & ~in[3] & ~in[4] & ~in[5] & ~in[6] & in[7]) |
       (~in[0] & ~in[3] & ~in[4] & ~in[5] & in[6]) |
       (~in[0] & ~in[3] & ~in[4] & ~in[5] & ~in[6] & ~in[7] & ~in[8] & ~in[0]));
	   
	   
	assign #5 out[2] = ~(~in[0] & ~in[1] & ~in[3] & ~in[4] & in[5]);
	   
	assign #5 out[3] = ~(~in[0] & ~in[3] & in[4] & ~in[5] & in[6] & in[7] & in[8]);
	   
	assign #5 out[4] = ~(in[2] & ~in[3] & in[4] & in[5] & in[6] & in[7]);

	assign #5 out[5] = ~((~in[0] & ~in[3] & in[4]) |
       (~in[0] & ~in[3] & ~in[4] & ~in[5] & ~in[6] & ~in[7] & ~in[8] & in[9]));

	assign #5 out[6] = ~((~in[0] & in[3]) |
       (~in[0] & in[1] & ~in[3] & ~in[4] & in[5]));

	assign #5 out[7] = ~((~in[0] & in[3]) |
       (~in[0] & in[1] & ~in[3] & ~in[4] & in[5]) |
       (~in[0] & ~in[3] & ~in[4] & ~in[5] & ~in[6] & ~in[7] & in[8]) |
       (~in[0] & ~in[3] & ~in[4] & ~in[5] & ~in[6] & in[7]) |
       (~in[0] & ~in[3] & ~in[4] & ~in[5] & in[6]) |
       (~in[0] & ~in[3] & ~in[4] & ~in[5] & ~in[6] & ~in[7] & ~in[8] & ~in[9]) |
       (~in[0] & ~in[1] & ~in[3] & ~in[4] & in[5]));
endmodule

Aliens/verilog/PAL16L8_053326_D21_TEST.v
//PAL16L8_053326_D21_TEST.v
//PAL 053327-D21 Testbench.
//used in Aliens Konami Arcade PCB.
//Author: RndMnkIII. 10/2019. (@RndMnkIII).
//---------------------------------------------------------
//iverilog -o pald21_sim PAL16L8_053326_D21.v PAL16L8_053326_D21_TEST.v
//vvp pald21_sim
//gtkwave PAL16L8_053326_D21_TEST.vcd

`timescale 1ns / 1ns
module PAL16L8_053326_D21_TEST;
  reg [9:0] x;
  reg AS, BK4, INIT, MAF, MAE, MAD, MAC, MAB, MAA, WOCO;
  wire D20_8, WORK, BANK, D20_13, D20_16, D18_5__D20_2, PROG, C19_1;

  //PAL16L8_053326_D21 pald21(in, out);
  PAL16L8_053326_D21 pald21(.in({AS,BK4,INIT,MAF,MAE,MAD,MAC,MAB,MAA,WOCO}), .out({D20_8, WORK, BANK, D20_13, D20_16, D18_5__D20_2, PROG, C19_1}));
  
  initial
    begin
	  $dumpfile ("PAL16L8_053326_D21_TEST.vcd");
	  $dumpvars (0, PAL16L8_053326_D21_TEST); //0 all variables included
      $monitor ($time,"\nInputs:\nAS\tBK4\tINIT\tMAF\tMAE\tMAD\tMAC\tMAB\tMAA\tWOCO\n--\t---\t----\t---\t---\t---\t---\t---\t---\t----\n%b\t%b\t%b\t%b\t%b\t%b\t%b\t%b\t%b\t%b\n\nOutputs:\nD20_8\tWORK\tBANK\tD20_13\tD20_16\tD18_5\tPROG\tC19_1\n-----\t----\t----\t-----\t------\t-----\t----\t-----\n%b\t%b\t%b\t%b\t%b\t%b\t%b\t%b\n\n----------------------------------------------------------------------------\n\n", AS, BK4, INIT, MAF, MAE, MAD, MAC, MAB, MAA, WOCO,D20_8, WORK, BANK, D20_13, D20_16, D18_5__D20_2, PROG, C19_1);
	  
	for (x=0; x < 1023; x= x+1)
		begin
    //Suponemos un periodo máximo de 1/25MHz
			#40 ; {AS, BK4, INIT, MAF, MAE, MAD, MAC, MAB, MAA, WOCO} = x;
		end // end of for loop 
      #40 $finish;
    end
endmodule

Aliens/verilog/PAL16L8_053326_D21_TEST.vcd
$date
	Thu Oct 10 19:20:09 2019
$end
$version
	Icarus Verilog
$end
$timescale
	1ns
$end
$scope module PAL16L8_053326_D21_TEST $end
$var wire 1 ! WORK $end
$var wire 1 " PROG $end
$var wire 1 # D20_8 $end
$var wire 1 $ D20_16 $end
$var wire 1 % D20_13 $end
$var wire 1 & D18_5__D20_2 $end
$var wire 1 ' C19_1 $end
$var wire 1 ( BANK $end
$var reg 1 ) AS $end
$var reg 1 * BK4 $end
$var reg 1 + INIT $end
$var reg 1 , MAA $end
$var reg 1 - MAB $end
$var reg 1 . MAC $end
$var reg 1 / MAD $end
$var reg 1 0 MAE $end
$var reg 1 1 MAF $end
$var reg 1 2 WOCO $end
$var reg 10 3 x [9:0] $end
$scope module pald21 $end
$var wire 10 4 in [9:0] $end
$var wire 8 5 out [7:0] $end
$upscope $end
$upscope $end
$enddefinitions $end
#0
$dumpvars
bx 5
bx 4
b0 3
x2
x1
x0
x/
x.
x-
x,
x+
x*
x)
x(
x'
x&
x%
x$
x#
x"
x!
$end
#40
b1 3
0)
0*
0+
01
00
0/
0.
0-
0,
b0 4
02
#45
0#
0"
1(
1!
1'
1$
1%
1&
b1111101 5
#80
b10 3
b1 4
12
#85
1#
1"
b11111111 5
#120
b11 3
1,
b10 4
02
#125
0#
0"
b1111101 5
#160
b100 3
b11 4
12
#165
1#
1"
b11111111 5
#200
b101 3
1-
0,
b100 4
02
#205
0#
0"
b1111101 5
#240
b110 3
b101 4
12
#245
1#
1"
b11111111 5
#280
b111 3
1,
b110 4
02
#285
0#
0"
b1111101 5
#320
b1000 3
b111 4
12
#325
1#
1"
b11111111 5
#360
b1001 3
1.
0-
0,
b1000 4
02
#365
0#
0!
b111111 5
#400
b1010 3
b1001 4
12
#405
1#
1!
b11111111 5
#440
b1011 3
1,
b1010 4
02
#445
0#
0!
b111111 5
#480
b1100 3
b1011 4
12
#485
1#
1!
b11111111 5
#520
b1101 3
1-
0,
b1100 4
02
#525
0#
0!
b111111 5
#560
b1110 3
b1101 4
12
#565
1#
1!
b11111111 5
#600
b1111 3
1,
b1110 4
02
#605
0#
0!
b111111 5
#640
b10000 3
b1111 4
12
#645
1#
1!
b11111111 5
#680
b10001 3
1/
0.
0-
0,
b10000 4
02
#685
0(
b11011111 5
#720
b10010 3
b10001 4
12
#725
1(
b11111111 5
#760
b10011 3
1,
b10010 4
02
#765
0(
b11011111 5
#800
b10100 3
b10011 4
12
#805
1(
b11111111 5
#840
b10101 3
1-
0,
b10100 4
02
#845
0(
b11011111 5
#880
b10110 3
b10101 4
12
#885
1(
b11111111 5
#920
b10111 3
1,
b10110 4
02
#925
0(
b11011111 5
#960
b11000 3
b10111 4
12
#965
1(
b11111111 5
#1000
b11001 3
1.
0-
0,
b11000 4
02
#1005
0#
0!
b111111 5
#1040
b11010 3
b11001 4
12
#1045
1#
1!
b11111111 5
#1080
b11011 3
1,
b11010 4
02
#1085
0#
0!
b111111 5
#1120
b11100 3
b11011 4
12
#1125
1#
1!
b11111111 5
#1160
b11101 3
1-
0,
b11100 4
02
#1165
0#
0!
b111111 5
#1200
b11110 3
b11101 4
12
#1205
1#
1!
b11111111 5
#1240
b11111 3
1,
b11110 4
02
#1245
0#
0!
b111111 5
#1280
b100000 3
b11111 4
12
#1285
1#
1!
b11111111 5
#1320
b100001 3
10
0/
0.
0-
0,
b100000 4
02
#1325
0#
0&
b1111011 5
#1360
b100010 3
b100001 4
12
#1365
1#
1&
b11111111 5
#1400
b100011 3
1,
b100010 4
02
#1405
0#
0!
b111111 5
#1440
b100100 3
b100011 4
12
#1445
1#
1!
b11111111 5
#1480
b100101 3
1-
0,
b100100 4
02
#1485
0#
0&
b1111011 5
#1520
b100110 3
b100101 4
12
#1525
1#
1&
b11111111 5
#1560
b100111 3
1,
b100110 4
02
#1565
0#
0!
b111111 5
#1600
b101000 3
b100111 4
12
#1605
1#
1!
b11111111 5
#1640
b101001 3
1.
0-
0,
b101000 4
02
#1645
0#
0!
b111111 5
#1680
b101010 3
b101001 4
12
#1685
1#
1!
b11111111 5
#1720
b101011 3
1,
b101010 4
02
#1725
0#
0!
b111111 5
#1760
b101100 3
b101011 4
12
#1765
1#
1!
b11111111 5
#1800
b101101 3
1-
0,
b101100 4
02
#1805
0#
0!
b111111 5
#1840
b101110 3
b101101 4
12
#1845
1#
1!
b11111111 5
#1880
b101111 3
1,
b101110 4
02
#1885
0#
0!
b111111 5
#1920
b110000 3
b101111 4
12
#1925
1#
1!
b11111111 5
#1960
b110001 3
1/
0.
0-
0,
b110000 4
02
#1965
0(
b11011111 5
#2000
b110010 3
b110001 4
12
#2005
1(
b11111111 5
#2040
b110011 3
1,
b110010 4
02
#2045
0(
b11011111 5
#2080
b110100 3
b110011 4
12
#2085
1(
b11111111 5
#2120
b110101 3
1-
0,
b110100 4
02
#2125
0(
b11011111 5
#2160
b110110 3
b110101 4
12
#2165
1(
b11111111 5
#2200
b110111 3
1,
b110110 4
02
#2205
0(
b11011111 5
#2240
b111000 3
b110111 4
12
#2245
1(
b11111111 5
#2280
b111001 3
1.
0-
0,
b111000 4
02
#2285
0#
0!
b111111 5
#2320
b111010 3
b111001 4
12
#2325
1#
1!
b11111111 5
#2360
b111011 3
1,
b111010 4
02
#2365
0#
0!
b111111 5
#2400
b111100 3
b111011 4
12
#2405
1#
1!
b11111111 5
#2440
b111101 3
1-
0,
b111100 4
02
#2445
0#
0!
b111111 5
#2480
b111110 3
b111101 4
12
#2485
1#
1!
b11111111 5
#2520
b111111 3
1,
b111110 4
02
#2525
0#
0!
b111111 5
#2560
b1000000 3
b111111 4
12
#2565
1#
1!
b11111111 5
#2600
b1000001 3
11
00
0/
0.
0-
0,
b1000000 4
02
#2605
0#
0"
b1111101 5
#2640
b1000010 3
b1000001 4
12
#2645
1#
1"
b11111111 5
#2680
b1000011 3
1,
b1000010 4
02
#2685
0#
0"
b1111101 5
#2720
b1000100 3
b1000011 4
12
#2725
1#
1"
b11111111 5
#2760
b1000101 3
1-
0,
b1000100 4
02
#2765
0#
0"
b1111101 5
#2800
b1000110 3
b1000101 4
12
#2805
1#
1"
b11111111 5
#2840
b1000111 3
1,
b1000110 4
02
#2845
0#
0"
b1111101 5
#2880
b1001000 3
b1000111 4
12
#2885
1#
1"
b11111111 5
#2920
b1001001 3
1.
0-
0,
b1001000 4
02
#2925
0#
0!
b111111 5
#2960
b1001010 3
b1001001 4
12
#2965
1#
1!
b11111111 5
#3000
b1001011 3
1,
b1001010 4
02
#3005
0#
0!
b111111 5
#3040
b1001100 3
b1001011 4
12
#3045
1#
1!
b11111111 5
#3080
b1001101 3
1-
0,
b1001100 4
02
#3085
0#
0!
b111111 5
#3120
b1001110 3
b1001101 4
12
#3125
1#
1!
b11111111 5
#3160
b1001111 3
1,
b1001110 4
02
#3165
0#
0!
b111111 5
#3200
b1010000 3
b1001111 4
12
#3205
1#
1!
b11111111 5
#3240
b1010001 3
1/
0.
0-
0,
b1010000 4
02
#3245
0(
b11011111 5
#3280
b1010010 3
b1010001 4
12
#3285
1(
b11111111 5
#3320
b1010011 3
1,
b1010010 4
02
#3325
0(
b11011111 5
#3360
b1010100 3
b1010011 4
12
#3365
1(
b11111111 5
#3400
b1010101 3
1-
0,
b1010100 4
02
#3405
0(
b11011111 5
#3440
b1010110 3
b1010101 4
12
#3445
1(
b11111111 5
#3480
b1010111 3
1,
b1010110 4
02
#3485
0(
b11011111 5
#3520
b1011000 3
b1010111 4
12
#3525
1(
b11111111 5
#3560
b1011001 3
1.
0-
0,
b1011000 4
02
#3565
0#
0!
b111111 5
#3600
b1011010 3
b1011001 4
12
#3605
1#
1!
b11111111 5
#3640
b1011011 3
1,
b1011010 4
02
#3645
0#
0!
b111111 5
#3680
b1011100 3
b1011011 4
12
#3685
1#
1!
b11111111 5
#3720
b1011101 3
1-
0,
b1011100 4
02
#3725
0#
0!
b111111 5
#3760
b1011110 3
b1011101 4
12
#3765
1#
1!
b11111111 5
#3800
b1011111 3
1,
b1011110 4
02
#3805
0#
0!
b111111 5
#3840
b1100000 3
b1011111 4
12
#3845
1#
1!
b11111111 5
#3880
b1100001 3
10
0/
0.
0-
0,
b1100000 4
02
#3885
0#
0&
b1111011 5
#3920
b1100010 3
b1100001 4
12
#3925
1#
1&
b11111111 5
#3960
b1100011 3
1,
b1100010 4
02
#3965
0#
0!
b111111 5
#4000
b1100100 3
b1100011 4
12
#4005
1#
1!
b11111111 5
#4040
b1100101 3
1-
0,
b1100100 4
02
#4045
0#
0&
b1111011 5
#4080
b1100110 3
b1100101 4
12
#4085
1#
1&
b11111111 5
#4120
b1100111 3
1,
b1100110 4
02
#4125
0#
0!
b111111 5
#4160
b1101000 3
b1100111 4
12
#4165
1#
1!
b11111111 5
#4200
b1101001 3
1.
0-
0,
b1101000 4
02
#4205
0#
0!
b111111 5
#4240
b1101010 3
b1101001 4
12
#4245
1#
1!
b11111111 5
#4280
b1101011 3
1,
b1101010 4
02
#4285
0#
0!
b111111 5
#4320
b1101100 3
b1101011 4
12
#4325
1#
1!
b11111111 5
#4360
b1101101 3
1-
0,
b1101100 4
02
#4365
0#
0!
b111111 5
#4400
b1101110 3
b1101101 4
12
#4405
1#
1!
b11111111 5
#4440
b1101111 3
1,
b1101110 4
02
#4445
0#
0!
b111111 5
#4480
b1110000 3
b1101111 4
12
#4485
1#
1!
b11111111 5
#4520
b1110001 3
1/
0.
0-
0,
b1110000 4
02
#4525
0(
b11011111 5
#4560
b1110010 3
b1110001 4
12
#4565
1(
b11111111 5
#4600
b1110011 3
1,
b1110010 4
02
#4605
0(
b11011111 5
#4640
b1110100 3
b1110011 4
12
#4645
1(
b11111111 5
#4680
b1110101 3
1-
0,
b1110100 4
02
#4685
0(
b11011111 5
#4720
b1110110 3
b1110101 4
12
#4725
1(
b11111111 5
#4760
b1110111 3
1,
b1110110 4
02
#4765
0(
b11011111 5
#4800
b1111000 3
b1110111 4
12
#4805
1(
b11111111 5
#4840
b1111001 3
1.
0-
0,
b1111000 4
02
#4845
0#
0!
b111111 5
#4880
b1111010 3
b1111001 4
12
#4885
1#
1!
b11111111 5
#4920
b1111011 3
1,
b1111010 4
02
#4925
0#
0!
b111111 5
#4960
b1111100 3
b1111011 4
12
#4965
1#
1!
b11111111 5
#5000
b1111101 3
1-
0,
b1111100 4
02
#5005
0#
0!
b111111 5
#5040
b1111110 3
b1111101 4
12
#5045
1#
1!
b11111111 5
#5080
b1111111 3
1,
b1111110 4
02
#5085
0#
0!
b111111 5
#5120
b10000000 3
b1111111 4
12
#5125
1#
1!
b11111111 5
#5160
b10000001 3
1+
01
00
0/
0.
0-
0,
b10000000 4
02
#5165
0#
0"
b1111101 5
#5200
b10000010 3
b10000001 4
12
#5205
1#
1"
b11111111 5
#5240
b10000011 3
1,
b10000010 4
02
#5245
0#
0"
b1111101 5
#5280
b10000100 3
b10000011 4
12
#5285
1#
1"
b11111111 5
#5320
b10000101 3
1-
0,
b10000100 4
02
#5325
0#
0"
b1111101 5
#5360
b10000110 3
b10000101 4
12
#5365
1#
1"
b11111111 5
#5400
b10000111 3
1,
b10000110 4
02
#5405
0#
0"
b1111101 5
#5440
b10001000 3
b10000111 4
12
#5445
1#
1"
b11111111 5
#5480
b10001001 3
1.
0-
0,
b10001000 4
02
#5485
0#
0!
b111111 5
#5520
b10001010 3
b10001001 4
12
#5525
1#
1!
b11111111 5
#5560
b10001011 3
1,
b10001010 4
02
#5565
0#
0!
b111111 5
#5600
b10001100 3
b10001011 4
12
#5605
1#
1!
b11111111 5
#5640
b10001101 3
1-
0,
b10001100 4
02
#5645
0#
0!
b111111 5
#5680
b10001110 3
b10001101 4
12
#5685
1#
1!
b11111111 5
#5720
b10001111 3
1,
b10001110 4
02
#5725
0#
0!
b111111 5
#5760
b10010000 3
b10001111 4
12
#5765
1#
1!
b11111111 5
#5800
b10010001 3
1/
0.
0-
0,
b10010000 4
02
#5805
0(
b11011111 5
#5840
b10010010 3
b10010001 4
12
#5845
1(
b11111111 5
#5880
b10010011 3
1,
b10010010 4
02
#5885
0(
b11011111 5
#5920
b10010100 3
b10010011 4
12
#5925
1(
b11111111 5
#5960
b10010101 3
1-
0,
b10010100 4
02
#5965
0(
b11011111 5
#6000
b10010110 3
b10010101 4
12
#6005
1(
b11111111 5
#6040
b10010111 3
1,
b10010110 4
02
#6045
0(
b11011111 5
#6080
b10011000 3
b10010111 4
12
#6085
1(
b11111111 5
#6120
b10011001 3
1.
0-
0,
b10011000 4
02
#6125
0#
0!
b111111 5
#6160
b10011010 3
b10011001 4
12
#6165
1#
1!
b11111111 5
#6200
b10011011 3
1,
b10011010 4
02
#6205
0#
0!
b111111 5
#6240
b10011100 3
b10011011 4
12
#6245
1#
1!
b11111111 5
#6280
b10011101 3
1-
0,
b10011100 4
02
#6285
0#
0!
b111111 5
#6320
b10011110 3
b10011101 4
12
#6325
1#
1!
b11111111 5
#6360
b10011111 3
1,
b10011110 4
02
#6365
0#
0!
b111111 5
#6400
b10100000 3
b10011111 4
12
#6405
1#
1!
b11111111 5
#6440
b10100001 3
10
0/
0.
0-
0,
b10100000 4
02
#6445
0#
0&
b1111011 5
#6480
b10100010 3
b10100001 4
12
#6485
1#
1&
b11111111 5
#6520
b10100011 3
1,
b10100010 4
02
#6525
0#
0!
b111111 5
#6560
b10100100 3
b10100011 4
12
#6565
1#
1!
b11111111 5
#6600
b10100101 3
1-
0,
b10100100 4
02
#6605
0#
0&
b1111011 5
#6640
b10100110 3
b10100101 4
12
#6645
1#
1&
b11111111 5
#6680
b10100111 3
1,
b10100110 4
02
#6685
0#
0!
b111111 5
#6720
b10101000 3
b10100111 4
12
#6725
1#
1!
b11111111 5
#6760
b10101001 3
1.
0-
0,
b10101000 4
02
#6765
0#
0!
b111111 5
#6800
b10101010 3
b10101001 4
12
#6805
1#
1!
b11111111 5
#6840
b10101011 3
1,
b10101010 4
02
#6845
0#
0!
b111111 5
#6880
b10101100 3
b10101011 4
12
#6885
1#
1!
b11111111 5
#6920
b10101101 3
1-
0,
b10101100 4
02
#6925
0#
0!
b111111 5
#6960
b10101110 3
b10101101 4
12
#6965
1#
1!
b11111111 5
#7000
b10101111 3
1,
b10101110 4
02
#7005
0#
0!
b111111 5
#7040
b10110000 3
b10101111 4
12
#7045
1#
1!
b11111111 5
#7080
b10110001 3
1/
0.
0-
0,
b10110000 4
02
#7085
0(
b11011111 5
#7120
b10110010 3
b10110001 4
12
#7125
1(
b11111111 5
#7160
b10110011 3
1,
b10110010 4
02
#7165
0(
b11011111 5
#7200
b10110100 3
b10110011 4
12
#7205
1(
b11111111 5
#7240
b10110101 3
1-
0,
b10110100 4
02
#7245
0(
b11011111 5
#7280
b10110110 3
b10110101 4
12
#7285
1(
b11111111 5
#7320
b10110111 3
1,
b10110110 4
02
#7325
0(
b11011111 5
#7360
b10111000 3
b10110111 4
12
#7365
1(
b11111111 5
#7400
b10111001 3
1.
0-
0,
b10111000 4
02
#7405
0#
0!
b111111 5
#7440
b10111010 3
b10111001 4
12
#7445
1#
1!
b11111111 5
#7480
b10111011 3
1,
b10111010 4
02
#7485
0#
0!
b111111 5
#7520
b10111100 3
b10111011 4
12
#7525
1#
1!
b11111111 5
#7560
b10111101 3
1-
0,
b10111100 4
02
#7565
0#
0!
b111111 5
#7600
b10111110 3
b10111101 4
12
#7605
1#
1!
b11111111 5
#7640
b10111111 3
1,
b10111110 4
02
#7645
0#
0!
b111111 5
#7680
b11000000 3
b10111111 4
12
#7685
1#
1!
b11111111 5
#7720
b11000001 3
11
00
0/
0.
0-
0,
b11000000 4
02
#7725
0#
0"
b1111101 5
#7760
b11000010 3
b11000001 4
12
#7765
1#
1"
b11111111 5
#7800
b11000011 3
1,
b11000010 4
02
#7805
0#
0"
b1111101 5
#7840
b11000100 3
b11000011 4
12
#7845
1#
1"
b11111111 5
#7880
b11000101 3
1-
0,
b11000100 4
02
#7885
0#
0"
b1111101 5
#7920
b11000110 3
b11000101 4
12
#7925
1#
1"
b11111111 5
#7960
b11000111 3
1,
b11000110 4
02
#7965
0#
0"
b1111101 5
#8000
b11001000 3
b11000111 4
12
#8005
1#
1"
b11111111 5
#8040
b11001001 3
1.
0-
0,
b11001000 4
02
#8045
0#
0!
b111111 5
#8080
b11001010 3
b11001001 4
12
#8085
1#
1!
b11111111 5
#8120
b11001011 3
1,
b11001010 4
02
#8125
0#
0!
b111111 5
#8160
b11001100 3
b11001011 4
12
#8165
1#
1!
b11111111 5
#8200
b11001101 3
1-
0,
b11001100 4
02
#8205
0#
0!
b111111 5
#8240
b11001110 3
b11001101 4
12
#8245
1#
1!
b11111111 5
#8280
b11001111 3
1,
b11001110 4
02
#8285
0#
0!
b111111 5
#8320
b11010000 3
b11001111 4
12
#8325
1#
1!
b11111111 5
#8360
b11010001 3
1/
0.
0-
0,
b11010000 4
02
#8365
0(
b11011111 5
#8400
b11010010 3
b11010001 4
12
#8405
1(
b11111111 5
#8440
b11010011 3
1,
b11010010 4
02
#8445
0(
b11011111 5
#8480
b11010100 3
b11010011 4
12
#8485
1(
b11111111 5
#8520
b11010101 3
1-
0,
b11010100 4
02
#8525
0(
b11011111 5
#8560
b11010110 3
b11010101 4
12
#8565
1(
b11111111 5
#8600
b11010111 3
1,
b11010110 4
02
#8605
0(
b11011111 5
#8640
b11011000 3
b11010111 4
12
#8645
1(
b11111111 5
#8680
b11011001 3
1.
0-
0,
b11011000 4
02
#8685
0#
0!
b111111 5
#8720
b11011010 3
b11011001 4
12
#8725
1#
1!
b11111111 5
#8760
b11011011 3
1,
b11011010 4
02
#8765
0#
0!
b111111 5
#8800
b11011100 3
b11011011 4
12
#8805
1#
1!
b11111111 5
#8840
b11011101 3
1-
0,
b11011100 4
02
#8845
0#
0!
b111111 5
#8880
b11011110 3
b11011101 4
12
#8885
1#
1!
b11111111 5
#8920
b11011111 3
1,
b11011110 4
02
#8925
0#
0!
b111111 5
#8960
b11100000 3
b11011111 4
12
#8965
1#
1!
b11111111 5
#9000
b11100001 3
10
0/
0.
0-
0,
b11100000 4
02
#9005
0#
0&
b1111011 5
#9040
b11100010 3
b11100001 4
12
#9045
1#
1&
b11111111 5
#9080
b11100011 3
1,
b11100010 4
02
#9085
0#
0!
b111111 5
#9120
b11100100 3
b11100011 4
12
#9125
1#
1!
b11111111 5
#9160
b11100101 3
1-
0,
b11100100 4
02
#9165
0#
0&
b1111011 5
#9200
b11100110 3
b11100101 4
12
#9205
1#
1&
b11111111 5
#9240
b11100111 3
1,
b11100110 4
02
#9245
0#
0!
b111111 5
#9280
b11101000 3
b11100111 4
12
#9285
1#
1!
b11111111 5
#9320
b11101001 3
1.
0-
0,
b11101000 4
02
#9325
0#
0!
b111111 5
#9360
b11101010 3
b11101001 4
12
#9365
1#
1!
b11111111 5
#9400
b11101011 3
1,
b11101010 4
02
#9405
0#
0!
b111111 5
#9440
b11101100 3
b11101011 4
12
#9445
1#
1!
b11111111 5
#9480
b11101101 3
1-
0,
b11101100 4
02
#9485
0#
0!
b111111 5
#9520
b11101110 3
b11101101 4
12
#9525
1#
1!
b11111111 5
#9560
b11101111 3
1,
b11101110 4
02
#9565
0#
0!
b111111 5
#9600
b11110000 3
b11101111 4
12
#9605
1#
1!
b11111111 5
#9640
b11110001 3
1/
0.
0-
0,
b11110000 4
02
#9645
0(
b11011111 5
#9680
b11110010 3
b11110001 4
12
#9685
1(
b11111111 5
#9720
b11110011 3
1,
b11110010 4
02
#9725
0(
b11011111 5
#9760
b11110100 3
b11110011 4
12
#9765
1(
b11111111 5
#9800
b11110101 3
1-
0,
b11110100 4
02
#9805
0%
0(
b11001111 5
#9840
b11110110 3
b11110101 4
12
#9845
1(
b11101111 5
#9880
b11110111 3
1,
b11110110 4
02
#9885
0(
b11001111 5
#9920
b11111000 3
b11110111 4
12
#9925
1(
b11101111 5
#9960
b11111001 3
1.
0-
0,
b11111000 4
02
#9965
0#
1%
0!
b111111 5
#10000
b11111010 3
b11111001 4
12
#10005
1#
1!
b11111111 5
#10040
b11111011 3
1,
b11111010 4
02
#10045
0#
0!
b111111 5
#10080
b11111100 3
b11111011 4
12
#10085
1#
1!
b11111111 5
#10120
b11111101 3
1-
0,
b11111100 4
02
#10125
0#
0!
b111111 5
#10160
b11111110 3
b11111101 4
12
#10165
1#
1!
b11111111 5
#10200
b11111111 3
1,
b11111110 4
02
#10205
0#
0!
b111111 5
#10240
b100000000 3
b11111111 4
12
#10245
1#
1!
b11111111 5
#10280
b100000001 3
1*
0+
01
00
0/
0.
0-
0,
b100000000 4
02
#10285
0#
0"
b1111101 5
#10320
b100000010 3
b100000001 4
12
#10325
1#
1"
b11111111 5
#10360
b100000011 3
1,
b100000010 4
02
#10365
0#
0"
b1111101 5
#10400
b100000100 3
b100000011 4
12
#10405
1#
1"
b11111111 5
#10440
b100000101 3
1-
0,
b100000100 4
02
#10445
0#
0"
b1111101 5
#10480
b100000110 3
b100000101 4
12
#10485
1#
1"
b11111111 5
#10520
b100000111 3
1,
b100000110 4
02
#10525
0#
0"
b1111101 5
#10560
b100001000 3
b100000111 4
12
#10565
1#
1"
b11111111 5
#10600
b100001001 3
1.
0-
0,
b100001000 4
02
#10605
0#
0!
b111111 5
#10640
b100001010 3
b100001001 4
12
#10645
1#
1!
b11111111 5
#10680
b100001011 3
1,
b100001010 4
02
#10685
0#
0!
b111111 5
#10720
b100001100 3
b100001011 4
12
#10725
1#
1!
b11111111 5
#10760
b100001101 3
1-
0,
b100001100 4
02
#10765
0#
0!
b111111 5
#10800
b100001110 3
b100001101 4
12
#10805
1#
1!
b11111111 5
#10840
b100001111 3
1,
b100001110 4
02
#10845
0#
0!
b111111 5
#10880
b100010000 3
b100001111 4
12
#10885
1#
1!
b11111111 5
#10920
b100010001 3
1/
0.
0-
0,
b100010000 4
02
#10925
0(
b11011111 5
#10960
b100010010 3
b100010001 4
12
#10965
1(
b11111111 5
#11000
b100010011 3
1,
b100010010 4
02
#11005
0(
b11011111 5
#11040
b100010100 3
b100010011 4
12
#11045
1(
b11111111 5
#11080
b100010101 3
1-
0,
b100010100 4
02
#11085
0(
b11011111 5
#11120
b100010110 3
b100010101 4
12
#11125
1(
b11111111 5
#11160
b100010111 3
1,
b100010110 4
02
#11165
0(
b11011111 5
#11200
b100011000 3
b100010111 4
12
#11205
1(
b11111111 5
#11240
b100011001 3
1.
0-
0,
b100011000 4
02
#11245
0#
0!
b111111 5
#11280
b100011010 3
b100011001 4
12
#11285
1#
1!
b11111111 5
#11320
b100011011 3
1,
b100011010 4
02
#11325
0#
0!
b111111 5
#11360
b100011100 3
b100011011 4
12
#11365
1#
1!
b11111111 5
#11400
b100011101 3
1-
0,
b100011100 4
02
#11405
0#
0!
b111111 5
#11440
b100011110 3
b100011101 4
12
#11445
1#
1!
b11111111 5
#11480
b100011111 3
1,
b100011110 4
02
#11485
0#
0!
b111111 5
#11520
b100100000 3
b100011111 4
12
#11525
1#
1!
b11111111 5
#11560
b100100001 3
10
0/
0.
0-
0,
b100100000 4
02
#11565
0#
0&
b1111011 5
#11600
b100100010 3
b100100001 4
12
#11605
1#
1&
b11111111 5
#11640
b100100011 3
1,
b100100010 4
02
#11645
0#
0!
b111111 5
#11680
b100100100 3
b100100011 4
12
#11685
1#
1!
b11111111 5
#11720
b100100101 3
1-
0,
b100100100 4
02
#11725
0#
0&
b1111011 5
#11760
b100100110 3
b100100101 4
12
#11765
1#
1&
b11111111 5
#11800
b100100111 3
1,
b100100110 4
02
#11805
0#
0!
b111111 5
#11840
b100101000 3
b100100111 4
12
#11845
1#
1!
b11111111 5
#11880
b100101001 3
1.
0-
0,
b100101000 4
02
#11885
0#
0!
b111111 5
#11920
b100101010 3
b100101001 4
12
#11925
1#
1!
b11111111 5
#11960
b100101011 3
1,
b100101010 4
02
#11965
0#
0!
b111111 5
#12000
b100101100 3
b100101011 4
12
#12005
1#
1!
b11111111 5
#12040
b100101101 3
1-
0,
b100101100 4
02
#12045
0#
0!
b111111 5
#12080
b100101110 3
b100101101 4
12
#12085
1#
1!
b11111111 5
#12120
b100101111 3
1,
b100101110 4
02
#12125
0#
0!
b111111 5
#12160
b100110000 3
b100101111 4
12
#12165
1#
1!
b11111111 5
#12200
b100110001 3
1/
0.
0-
0,
b100110000 4
02
#12205
0(
b11011111 5
#12240
b100110010 3
b100110001 4
12
#12245
1(
b11111111 5
#12280
b100110011 3
1,
b100110010 4
02
#12285
0(
b11011111 5
#12320
b100110100 3
b100110011 4
12
#12325
1(
b11111111 5
#12360
b100110101 3
1-
0,
b100110100 4
02
#12365
0(
b11011111 5
#12400
b100110110 3
b100110101 4
12
#12405
1(
b11111111 5
#12440
b100110111 3
1,
b100110110 4
02
#12445
0(
b11011111 5
#12480
b100111000 3
b100110111 4
12
#12485
1(
b11111111 5
#12520
b100111001 3
1.
0-
0,
b100111000 4
02
#12525
0#
0!
b111111 5
#12560
b100111010 3
b100111001 4
12
#12565
1#
1!
b11111111 5
#12600
b100111011 3
1,
b100111010 4
02
#12605
0#
0!
b111111 5
#12640
b100111100 3
b100111011 4
12
#12645
1#
1!
b11111111 5
#12680
b100111101 3
1-
0,
b100111100 4
02
#12685
0#
0!
b111111 5
#12720
b100111110 3
b100111101 4
12
#12725
1#
1!
b11111111 5
#12760
b100111111 3
1,
b100111110 4
02
#12765
0#
0!
b111111 5
#12800
b101000000 3
b100111111 4
12
