Aliens/verilog/PAL16L8_053326_D21.v
//PAL16L8_053326_D21.v
//Implementation of PAL 053326-D21 combinatorial logic
//used in Aliens Konami Arcade PCB.
//Converted to Verilog By RndMnkIII. 10/2019. (@RndMnkIII).
//---------------------------------------------------------
//Dumped from an unsecured PAL16L8, 
//converted to GAL16V8 with PALTOGAL 
//and tested by Caius (@Caius63417737).
//---------------------------------------------------------

module PAL16L8_053326_D21(in, out);
	input [9:0] in;
	//wire [9:0] in;
	output [7:0] out;
	
	assign out[0] = ~(~in[3] & ~in[4] & ~in[5] & ~in[6] & ~in[7] & ~in[8] & in[9]);
	
	assign out[1] = ~(~in[0] & ~in[3] & ~in[4] & ~in[5] & ~in[6] & ~in[7] & in[8] +
       ~in[0] & ~in[3] & ~in[4] & ~in[5] & ~in[6] & in[7] +
       ~in[0] & ~in[3] & ~in[4] & ~in[5] & in[6] +
       ~in[0] & ~in[3] & ~in[4] & ~in[5] & ~in[6] & ~in[7] & ~in[8] & ~in[0]);
	   
	   
	assign out[2] = ~(~in[0] & ~in[1] & ~in[3] & ~in[4] & in[5]);
	   
	assign out[3] = ~(~in[0] & ~in[3] & in[4] & ~in[5] & in[6] & in[7] & in[8]);
	   
	assign out[4] = ~(in[2] & ~in[3] & in[4] & in[5] & in[6] & in[7]);

	assign out[5] = ~(~in[0] & ~in[3] & in[4] +
       ~in[0] & ~in[3] & ~in[4] & ~in[5] & ~in[6] & ~in[7] & ~in[8] & in[9]);

	assign out[6] = ~(~in[0] & in[3] +
       ~in[0] & in[1] & ~in[3] & ~in[4] & in[5]);

	assign out[7] = ~(~in[0] & in[3] +
       ~in[0] & in[1] & ~in[3] & ~in[4] & in[5] +
       ~in[0] & ~in[3] & ~in[4] & ~in[5] & ~in[6] & ~in[7] & in[8] +
       ~in[0] & ~in[3] & ~in[4] & ~in[5] & ~in[6] & in[7] +
       ~in[0] & ~in[3] & ~in[4] & ~in[5] & in[6] +
       ~in[0] & ~in[3] & ~in[4] & ~in[5] & ~in[6] & ~in[7] & ~in[8] & ~in[9] +
       ~in[0] & ~in[1] & ~in[3] & ~in[4] & in[5]);
endmodule

Aliens/verilog/PAL16L8_053326_D21_TEST.v
//PAL16L8_053326_D21_TEST.v
//Implementation of PAL 053327-D20 combinatorial logic
//used in Aliens Konami Arcade PCB.
//Converted to Verilog By RndMnkIII. 10/2019. (@RndMnkIII).
//---------------------------------------------------------
//Dumped from an unsecured PAL16L8, 
//converted to GAL16V8 with PALTOGAL 
//and tested by Caius (@Caius63417737).
//---------------------------------------------------------
//iverilog -o pald21_sim PAL16L8_053326_D21.v PAL16L8_053326_D21_TEST.v
//vvp pald21_sim
//gtkwave PAL16L8_053326_D21_TEST.vcd

`timescale 1ns / 1ns
module PAL16L8_053326_D21_TEST;
  reg [9:0] x;
  reg AS, BK4, INIT, MAF, MAE, MAD, MAC, MAB, MAA, WOCO;
  wire D20_8, WORK, BANK, D20_13, D20_16, D18_5__D20_2, PROG, C19_1;

  //PAL16L8_053326_D21 pald21(in, out);
  PAL16L8_053326_D21 pald21(.in({AS,BK4,INIT,MAF,MAE,MAD,MAC,MAB,MAA,WOCO}), .out({D20_8, WORK, BANK, D20_13, D20_16, D18_5__D20_2, PROG, C19_1}));
  
  initial
    begin
	  $dumpfile ("PAL16L8_053326_D21_TEST.vcd");
	  $dumpvars (0, PAL16L8_053326_D21_TEST); //0 all variables included
      $monitor ($time,"\nInputs:\nAS\tBK4\tINIT\tMAF\tMAE\tMAD\tMAC\tMAB\tMAA\tWOCO\n--\t---\t----\t---\t---\t---\t---\t---\t---\t----\n%b\t%b\t%b\t%b\t%b\t%b\t%b\t%b\t%b\t%b\n\nOutputs:\nD20_8\tWORK\tBANK\tD20_13\tD20_16\tD18_5\tPROG\tC19_1\n-----\t----\t----\t-----\t------\t-----\t----\t-----\n%b\t%b\t%b\t%b\t%b\t%b\t%b\t%b\n\n----------------------------------------------------------------------------\n\n", AS, BK4, INIT, MAF, MAE, MAD, MAC, MAB, MAA, WOCO,D20_8, WORK, BANK, D20_13, D20_16, D18_5__D20_2, PROG, C19_1);
	  
	for (x=0; x < 1023; x= x+1)
		begin
			#10 ; {AS, BK4, INIT, MAF, MAE, MAD, MAC, MAB, MAA, WOCO} = x;
		end // end of for loop 
      #10 $finish;
    end
endmodule

Aliens/verilog/PAL16L8_053326_D21_TEST.vcd
$date
	Tue Oct 08 09:09:17 2019
$end
$version
	Icarus Verilog
$end
$timescale
	1ns
$end
$scope module PAL16L8_053326_D21_TEST $end
$var wire 1 ! WORK $end
$var wire 1 " PROG $end
$var wire 1 # D20_8 $end
$var wire 1 $ D20_16 $end
$var wire 1 % D20_13 $end
$var wire 1 & D18_5__D20_2 $end
$var wire 1 ' C19_1 $end
$var wire 1 ( BANK $end
$var reg 1 ) AS $end
$var reg 1 * BK4 $end
$var reg 1 + INIT $end
$var reg 1 , MAA $end
$var reg 1 - MAB $end
$var reg 1 . MAC $end
$var reg 1 / MAD $end
$var reg 1 0 MAE $end
$var reg 1 1 MAF $end
$var reg 1 2 WOCO $end
$var reg 10 3 x [9:0] $end
$scope module pald21 $end
$var wire 10 4 in [9:0] $end
$var wire 8 5 out [7:0] $end
$upscope $end
$upscope $end
$enddefinitions $end
#0
$dumpvars
bx 5
bx 4
b0 3
x2
x1
x0
x/
x.
x-
x,
x+
x*
x)
x(
x'
x&
x%
x$
x#
x"
x!
$end
#10
0"
1'
1(
1$
1%
1&
1!
1#
b11111101 5
b1 3
0)
0*
0+
01
00
0/
0.
0-
0,
b0 4
02
#20
1"
b11111111 5
b10 3
b1 4
12
#30
0"
b11111101 5
b11 3
1,
b10 4
02
#40
1"
b11111111 5
b100 3
b11 4
12
#50
0"
b11111101 5
b101 3
1-
0,
b100 4
02
#60
1"
b11111111 5
b110 3
b101 4
12
#70
0"
b11111101 5
b111 3
1,
b110 4
02
#80
1"
b11111111 5
b1000 3
b111 4
12
#90
b1001 3
1.
0-
0,
b1000 4
02
#100
b1010 3
b1001 4
12
#110
b1011 3
1,
b1010 4
02
#120
b1100 3
b1011 4
12
#130
b1101 3
1-
0,
b1100 4
02
#140
b1110 3
b1101 4
12
#150
b1111 3
1,
b1110 4
02
#160
b10000 3
b1111 4
12
#170
b10001 3
1/
0.
0-
0,
b10000 4
02
#180
b10010 3
b10001 4
12
#190
b10011 3
1,
b10010 4
02
#200
b10100 3
b10011 4
12
#210
b10101 3
1-
0,
b10100 4
02
#220
b10110 3
b10101 4
12
#230
b10111 3
1,
b10110 4
02
#240
b11000 3
b10111 4
12
#250
b11001 3
1.
0-
0,
b11000 4
02
#260
b11010 3
b11001 4
12
#270
b11011 3
1,
b11010 4
02
#280
b11100 3
b11011 4
12
#290
b11101 3
1-
0,
b11100 4
02
#300
b11110 3
b11101 4
12
#310
b11111 3
1,
b11110 4
02
#320
b100000 3
b11111 4
12
#330
0&
b11111011 5
b100001 3
10
0/
0.
0-
0,
b100000 4
02
#340
1&
b11111111 5
b100010 3
b100001 4
12
#350
0!
b10111111 5
b100011 3
1,
b100010 4
02
#360
1!
b11111111 5
b100100 3
b100011 4
12
#370
0&
b11111011 5
b100101 3
1-
0,
b100100 4
02
#380
1&
b11111111 5
b100110 3
b100101 4
12
#390
0!
b10111111 5
b100111 3
1,
b100110 4
02
#400
1!
b11111111 5
b101000 3
b100111 4
12
#410
b101001 3
1.
0-
0,
b101000 4
02
#420
b101010 3
b101001 4
12
#430
b101011 3
1,
b101010 4
02
#440
b101100 3
b101011 4
12
#450
b101101 3
1-
0,
b101100 4
02
#460
b101110 3
b101101 4
12
#470
b101111 3
1,
b101110 4
02
#480
b110000 3
b101111 4
12
#490
b110001 3
1/
0.
0-
0,
b110000 4
02
#500
b110010 3
b110001 4
12
#510
b110011 3
1,
b110010 4
02
#520
b110100 3
b110011 4
12
#530
b110101 3
1-
0,
b110100 4
02
#540
b110110 3
b110101 4
12
#550
b110111 3
1,
b110110 4
02
#560
b111000 3
b110111 4
12
#570
b111001 3
1.
0-
0,
b111000 4
02
#580
b111010 3
b111001 4
12
#590
b111011 3
1,
b111010 4
02
#600
b111100 3
b111011 4
12
#610
b111101 3
1-
0,
b111100 4
02
#620
b111110 3
b111101 4
12
#630
b111111 3
1,
b111110 4
02
#640
b1000000 3
b111111 4
12
#650
b1000001 3
11
00
0/
0.
0-
0,
b1000000 4
02
#660
b1000010 3
b1000001 4
12
#670
b1000011 3
1,
b1000010 4
02
#680
b1000100 3
b1000011 4
12
#690
b1000101 3
1-
0,
b1000100 4
02
#700
b1000110 3
b1000101 4
12
#710
b1000111 3
1,
b1000110 4
02
#720
b1001000 3
b1000111 4
12
#730
b1001001 3
1.
0-
0,
b1001000 4
02
#740
b1001010 3
b1001001 4
12
#750
b1001011 3
1,
b1001010 4
02
#760
b1001100 3
b1001011 4
12
#770
b1001101 3
1-
0,
b1001100 4
02
#780
b1001110 3
b1001101 4
12
#790
b1001111 3
1,
b1001110 4
02
#800
b1010000 3
b1001111 4
12
#810
b1010001 3
1/
0.
0-
0,
b1010000 4
02
#820
b1010010 3
b1010001 4
12
#830
b1010011 3
1,
b1010010 4
02
#840
b1010100 3
b1010011 4
12
#850
b1010101 3
1-
0,
b1010100 4
02
#860
b1010110 3
b1010101 4
12
#870
b1010111 3
1,
b1010110 4
02
#880
b1011000 3
b1010111 4
12
#890
b1011001 3
1.
0-
0,
b1011000 4
02
#900
b1011010 3
b1011001 4
12
#910
b1011011 3
1,
b1011010 4
02
#920
b1011100 3
b1011011 4
12
#930
b1011101 3
1-
0,
b1011100 4
02
#940
b1011110 3
b1011101 4
12
#950
b1011111 3
1,
b1011110 4
02
#960
b1100000 3
b1011111 4
12
#970
0&
b11111011 5
b1100001 3
10
0/
0.
0-
0,
b1100000 4
02
#980
1&
b11111111 5
b1100010 3
b1100001 4
12
#990
0!
b10111111 5
b1100011 3
1,
b1100010 4
02
#1000
1!
b11111111 5
b1100100 3
b1100011 4
12
#1010
0&
b11111011 5
b1100101 3
1-
0,
b1100100 4
02
#1020
1&
b11111111 5
b1100110 3
b1100101 4
12
#1030
0!
b10111111 5
b1100111 3
1,
b1100110 4
02
#1040
1!
b11111111 5
b1101000 3
b1100111 4
12
#1050
b1101001 3
1.
0-
0,
b1101000 4
02
#1060
b1101010 3
b1101001 4
12
#1070
b1101011 3
1,
b1101010 4
02
#1080
b1101100 3
b1101011 4
12
#1090
b1101101 3
1-
0,
b1101100 4
02
#1100
b1101110 3
b1101101 4
12
#1110
b1101111 3
1,
b1101110 4
02
#1120
b1110000 3
b1101111 4
12
#1130
b1110001 3
1/
0.
0-
0,
b1110000 4
02
#1140
b1110010 3
b1110001 4
12
#1150
b1110011 3
1,
b1110010 4
02
#1160
b1110100 3
b1110011 4
12
#1170
b1110101 3
1-
0,
b1110100 4
02
#1180
b1110110 3
b1110101 4
12
#1190
b1110111 3
1,
b1110110 4
02
#1200
b1111000 3
b1110111 4
12
#1210
b1111001 3
1.
0-
0,
b1111000 4
02
#1220
b1111010 3
b1111001 4
12
#1230
b1111011 3
1,
b1111010 4
02
#1240
b1111100 3
b1111011 4
12
#1250
b1111101 3
1-
0,
b1111100 4
02
#1260
b1111110 3
b1111101 4
12
#1270
b1111111 3
1,
b1111110 4
02
#1280
b10000000 3
b1111111 4
12
#1290
b10000001 3
1+
01
00
0/
0.
0-
0,
b10000000 4
02
#1300
b10000010 3
b10000001 4
12
#1310
b10000011 3
1,
b10000010 4
02
#1320
b10000100 3
b10000011 4
12
#1330
b10000101 3
1-
0,
b10000100 4
02
#1340
b10000110 3
b10000101 4
12
#1350
b10000111 3
1,
b10000110 4
02
#1360
b10001000 3
b10000111 4
12
#1370
b10001001 3
1.
0-
0,
b10001000 4
02
#1380
b10001010 3
b10001001 4
12
#1390
b10001011 3
1,
b10001010 4
02
#1400
b10001100 3
b10001011 4
12
#1410
b10001101 3
1-
0,
b10001100 4
02
#1420
b10001110 3
b10001101 4
12
#1430
b10001111 3
1,
b10001110 4
02
#1440
b10010000 3
b10001111 4
12
#1450
b10010001 3
1/
0.
0-
0,
b10010000 4
02
#1460
b10010010 3
b10010001 4
12
#1470
b10010011 3
1,
b10010010 4
02
#1480
b10010100 3
b10010011 4
12
#1490
b10010101 3
1-
0,
b10010100 4
02
#1500
b10010110 3
b10010101 4
12
#1510
b10010111 3
1,
b10010110 4
02
#1520
b10011000 3
b10010111 4
12
#1530
b10011001 3
1.
0-
0,
b10011000 4
02
#1540
b10011010 3
b10011001 4
12
#1550
b10011011 3
1,
b10011010 4
02
#1560
b10011100 3
b10011011 4
12
#1570
b10011101 3
1-
0,
b10011100 4
02
#1580
b10011110 3
b10011101 4
12
#1590
b10011111 3
1,
b10011110 4
02
#1600
b10100000 3
b10011111 4
12
#1610
0&
b11111011 5
b10100001 3
10
0/
0.
0-
0,
b10100000 4
02
#1620
1&
b11111111 5
b10100010 3
b10100001 4
12
#1630
0!
b10111111 5
b10100011 3
1,
b10100010 4
02
#1640
1!
b11111111 5
b10100100 3
b10100011 4
12
#1650
0&
b11111011 5
b10100101 3
1-
0,
b10100100 4
02
#1660
1&
b11111111 5
b10100110 3
b10100101 4
12
#1670
0!
b10111111 5
b10100111 3
1,
b10100110 4
02
#1680
1!
b11111111 5
b10101000 3
b10100111 4
12
#1690
b10101001 3
1.
0-
0,
b10101000 4
02
#1700
b10101010 3
b10101001 4
12
#1710
b10101011 3
1,
b10101010 4
02
#1720
b10101100 3
b10101011 4
12
#1730
b10101101 3
1-
0,
b10101100 4
02
#1740
b10101110 3
b10101101 4
12
#1750
b10101111 3
1,
b10101110 4
02
#1760
b10110000 3
b10101111 4
12
#1770
b10110001 3
1/
0.
0-
0,
b10110000 4
02
#1780
b10110010 3
b10110001 4
12
#1790
b10110011 3
1,
b10110010 4
02
#1800
b10110100 3
b10110011 4
12
#1810
b10110101 3
1-
0,
b10110100 4
02
#1820
b10110110 3
b10110101 4
12
#1830
b10110111 3
1,
b10110110 4
02
#1840
b10111000 3
b10110111 4
12
#1850
b10111001 3
1.
0-
0,
b10111000 4
02
#1860
b10111010 3
b10111001 4
12
#1870
b10111011 3
1,
b10111010 4
02
#1880
b10111100 3
b10111011 4
12
#1890
b10111101 3
1-
0,
b10111100 4
02
#1900
b10111110 3
b10111101 4
12
#1910
b10111111 3
1,
b10111110 4
02
#1920
b11000000 3
b10111111 4
12
#1930
b11000001 3
11
00
0/
0.
0-
0,
b11000000 4
02
#1940
b11000010 3
b11000001 4
12
#1950
b11000011 3
1,
b11000010 4
02
#1960
b11000100 3
b11000011 4
12
#1970
b11000101 3
1-
0,
b11000100 4
02
#1980
b11000110 3
b11000101 4
12
#1990
b11000111 3
1,
b11000110 4
02
#2000
b11001000 3
b11000111 4
12
#2010
b11001001 3
1.
0-
0,
b11001000 4
02
#2020
b11001010 3
b11001001 4
12
#2030
b11001011 3
1,
b11001010 4
02
#2040
b11001100 3
b11001011 4
12
#2050
b11001101 3
1-
0,
b11001100 4
02
#2060
b11001110 3
b11001101 4
12
#2070
b11001111 3
1,
b11001110 4
02
#2080
b11010000 3
b11001111 4
12
#2090
b11010001 3
1/
0.
0-
0,
b11010000 4
02
#2100
b11010010 3
b11010001 4
12
#2110
b11010011 3
1,
b11010010 4
02
#2120
b11010100 3
b11010011 4
12
#2130
b11010101 3
1-
0,
b11010100 4
02
#2140
b11010110 3
b11010101 4
12
#2150
b11010111 3
1,
b11010110 4
02
#2160
b11011000 3
b11010111 4
12
#2170
b11011001 3
1.
0-
0,
b11011000 4
02
#2180
b11011010 3
b11011001 4
12
#2190
b11011011 3
1,
b11011010 4
02
#2200
b11011100 3
b11011011 4
12
#2210
b11011101 3
1-
0,
b11011100 4
02
#2220
b11011110 3
b11011101 4
12
#2230
b11011111 3
1,
b11011110 4
02
#2240
b11100000 3
b11011111 4
12
#2250
0&
b11111011 5
b11100001 3
10
0/
0.
0-
0,
b11100000 4
02
#2260
1&
b11111111 5
b11100010 3
b11100001 4
12
#2270
0!
b10111111 5
b11100011 3
1,
b11100010 4
02
#2280
1!
b11111111 5
b11100100 3
b11100011 4
12
#2290
0&
b11111011 5
b11100101 3
1-
0,
b11100100 4
02
#2300
1&
b11111111 5
b11100110 3
b11100101 4
12
#2310
0!
b10111111 5
b11100111 3
1,
b11100110 4
02
#2320
1!
b11111111 5
b11101000 3
b11100111 4
12
#2330
b11101001 3
1.
0-
0,
b11101000 4
02
#2340
b11101010 3
b11101001 4
12
#2350
b11101011 3
1,
b11101010 4
02
#2360
b11101100 3
b11101011 4
12
#2370
b11101101 3
1-
0,
b11101100 4
02
#2380
b11101110 3
b11101101 4
12
#2390
b11101111 3
1,
b11101110 4
02
#2400
b11110000 3
b11101111 4
12
#2410
b11110001 3
1/
0.
0-
0,
b11110000 4
02
#2420
b11110010 3
b11110001 4
12
#2430
b11110011 3
1,
b11110010 4
02
#2440
b11110100 3
b11110011 4
12
#2450
0%
b11101111 5
b11110101 3
1-
0,
b11110100 4
02
#2460
b11110110 3
b11110101 4
12
#2470
b11110111 3
1,
b11110110 4
02
#2480
b11111000 3
b11110111 4
12
#2490
1%
b11111111 5
b11111001 3
1.
0-
0,
b11111000 4
02
#2500
b11111010 3
b11111001 4
12
#2510
b11111011 3
1,
b11111010 4
02
#2520
b11111100 3
b11111011 4
12
#2530
b11111101 3
1-
0,
b11111100 4
02
#2540
b11111110 3
b11111101 4
12
#2550
b11111111 3
1,
b11111110 4
02
#2560
b100000000 3
b11111111 4
12
#2570
b100000001 3
1*
0+
01
00
0/
0.
0-
0,
b100000000 4
02
#2580
b100000010 3
b100000001 4
12
#2590
b100000011 3
1,
b100000010 4
02
#2600
b100000100 3
b100000011 4
12
#2610
b100000101 3
1-
0,
b100000100 4
02
#2620
b100000110 3
b100000101 4
12
#2630
b100000111 3
1,
b100000110 4
02
#2640
b100001000 3
b100000111 4
12
#2650
b100001001 3
1.
0-
0,
b100001000 4
02
#2660
b100001010 3
b100001001 4
12
#2670
b100001011 3
1,
b100001010 4
02
#2680
b100001100 3
b100001011 4
12
#2690
b100001101 3
1-
0,
b100001100 4
02
#2700
b100001110 3
b100001101 4
12
#2710
b100001111 3
1,
b100001110 4
02
#2720
b100010000 3
b100001111 4
12
#2730
b100010001 3
1/
0.
0-
0,
b100010000 4
02
#2740
b100010010 3
b100010001 4
12
#2750
b100010011 3
1,
b100010010 4
02
#2760
b100010100 3
b100010011 4
12
#2770
b100010101 3
1-
0,
b100010100 4
02
#2780
b100010110 3
b100010101 4
12
#2790
b100010111 3
1,
b100010110 4
02
#2800
b100011000 3
b100010111 4
12
#2810
b100011001 3
1.
0-
0,
b100011000 4
02
#2820
b100011010 3
b100011001 4
12
#2830
b100011011 3
1,
b100011010 4
02
#2840
b100011100 3
b100011011 4
12
#2850
b100011101 3
1-
0,
b100011100 4
02
#2860
b100011110 3
b100011101 4
12
#2870
b100011111 3
1,
b100011110 4
02
#2880
b100100000 3
b100011111 4
12
#2890
0&
b11111011 5
b100100001 3
10
0/
0.
0-
0,
b100100000 4
02
#2900
1&
b11111111 5
b100100010 3
b100100001 4
12
#2910
0!
b10111111 5
b100100011 3
1,
b100100010 4
02
#2920
1!
b11111111 5
b100100100 3
b100100011 4
12
#2930
0&
b11111011 5
b100100101 3
1-
0,
b100100100 4
02
#2940
1&
b11111111 5
b100100110 3
b100100101 4
12
#2950
0!
b10111111 5
b100100111 3
1,
b100100110 4
02
#2960
1!
b11111111 5
b100101000 3
b100100111 4
12
#2970
b100101001 3
1.
0-
0,
b100101000 4
02
#2980
b100101010 3
b100101001 4
12
#2990
b100101011 3
1,
b100101010 4
02
#3000
b100101100 3
b100101011 4
12
#3010
b100101101 3
1-
0,
b100101100 4
02
#3020
b100101110 3
b100101101 4
12
#3030
b100101111 3
1,
b100101110 4
02
#3040
b100110000 3
b100101111 4
12
#3050
b100110001 3
1/
0.
0-
0,
b100110000 4
02
#3060
b100110010 3
b100110001 4
12
#3070
b100110011 3
1,
b100110010 4
02
#3080
b100110100 3
b100110011 4
12
#3090
b100110101 3
1-
0,
b100110100 4
02
#3100
b100110110 3
b100110101 4
12
#3110
b100110111 3
1,
b100110110 4
02
#3120
b100111000 3
b100110111 4
12
#3130
b100111001 3
1.
0-
0,
b100111000 4
02
#3140
b100111010 3
b100111001 4
12
#3150
b100111011 3
1,
b100111010 4
02
#3160
b100111100 3
b100111011 4
12
#3170
b100111101 3
1-
0,
b100111100 4
02
#3180
b100111110 3
b100111101 4
12
#3190
b100111111 3
1,
b100111110 4
02
#3200
b101000000 3
b100111111 4
12
#3210
b101000001 3
11
00
0/
0.
0-
0,
b101000000 4
02
#3220
b101000010 3
b101000001 4
12
#3230
b101000011 3
1,
b101000010 4
02
#3240
b101000100 3
b101000011 4
12
#3250
b101000101 3
1-
0,
b101000100 4
02
#3260
b101000110 3
b101000101 4
12
#3270
b101000111 3
1,
b101000110 4
02
#3280
b101001000 3
b101000111 4
12
#3290
b101001001 3
1.
0-
0,
b101001000 4
02
#3300
b101001010 3
b101001001 4
12
#3310
b101001011 3
1,
b101001010 4
02
#3320
b101001100 3
b101001011 4
12
#3330
b101001101 3
1-
0,
b101001100 4
02
#3340
b101001110 3
b101001101 4
12
#3350
b101001111 3
1,
b101001110 4
02
#3360
b101010000 3
b101001111 4
12
#3370
b101010001 3
1/
0.
0-
0,
b101010000 4
02
#3380
b101010010 3
b101010001 4
12
#3390
b101010011 3
1,
b101010010 4
02
#3400
b101010100 3
b101010011 4
12
#3410
b101010101 3
1-
0,
b101010100 4
02
#3420
b101010110 3
b101010101 4
12
#3430
b101010111 3
1,
b101010110 4
02
#3440
b101011000 3
b101010111 4
12
#3450
b101011001 3
1.
0-
0,
b101011000 4
02
#3460
b101011010 3
b101011001 4
12
#3470
b101011011 3
1,
b101011010 4
02
#3480
b101011100 3
b101011011 4
12
#3490
b101011101 3
1-
0,
b101011100 4
02
#3500
b101011110 3
b101011101 4
12
#3510
b101011111 3
1,
b101011110 4
02
#3520
b101100000 3
b101011111 4
12
#3530
0&
b11111011 5
b101100001 3
10
0/
0.
0-
0,
b101100000 4
02
#3540
1&
b11111111 5
b101100010 3
b101100001 4
12
#3550
0!
b10111111 5
b101100011 3
1,
b101100010 4
02
#3560
1!
b11111111 5
b101100100 3
b101100011 4
12
#3570
0&
b11111011 5
b101100101 3
1-
0,
b101100100 4
02
#3580
1&
b11111111 5
b101100110 3
b101100101 4
12
#3590
0!
b10111111 5
b101100111 3
1,
b101100110 4
02
#3600
1!
b11111111 5
b101101000 3
b101100111 4
12
#3610
b101101001 3
1.
0-
0,
b101101000 4
02
#3620
b101101010 3
b101101001 4
12
#3630
b101101011 3
1,
b101101010 4
02
#3640
b101101100 3
b101101011 4
12
#3650
b101101101 3
1-
0,
b101101100 4
02
#3660
b101101110 3
b101101101 4
12
#3670
b101101111 3
1,
b101101110 4
02
#3680
b101110000 3
b101101111 4
12
#3690
b101110001 3
1/
0.
0-
0,
b101110000 4
02
#3700
b101110010 3
b101110001 4
12
#3710
b101110011 3
1,
b101110010 4
02
#3720
b101110100 3
b101110011 4
12
#3730
b101110101 3
1-
0,
b101110100 4
02
#3740
b101110110 3
b101110101 4
12
#3750
b101110111 3
1,
b101110110 4
02
#3760
b101111000 3
b101110111 4
12
#3770
b101111001 3
1.
0-
0,
b101111000 4
02
#3780
b101111010 3
b101111001 4
12
#3790
b101111011 3
1,
b101111010 4
02
#3800
b101111100 3
b101111011 4
12
#3810
b101111101 3
1-
0,
b101111100 4
02
#3820
b101111110 3
b101111101 4
12
#3830
b101111111 3
1,
b101111110 4
02
#3840
b110000000 3
b101111111 4
12
#3850
b110000001 3
1+
01
00
0/
0.
0-
0,
b110000000 4
02
#3860
b110000010 3
b110000001 4
12
#3870
b110000011 3
1,
b110000010 4
02
#3880
b110000100 3
b110000011 4
12
#3890
b110000101 3
1-
0,
b110000100 4
02
#3900
b110000110 3
b110000101 4
12
#3910
b110000111 3
1,
b110000110 4
02
#3920
b110001000 3
b110000111 4
12
#3930
b110001001 3
1.
0-
0,
b110001000 4
02
#3940
b110001010 3
b110001001 4
12
#3950
b110001011 3
1,
b110001010 4
02
#3960
b110001100 3
b110001011 4
12
#3970
b110001101 3
1-
0,
b110001100 4
02
#3980
b110001110 3
b110001101 4
12
#3990
b110001111 3
1,
b110001110 4
02
#4000
b110010000 3
b110001111 4
12
#4010
b110010001 3
1/
0.
0-
0,
b110010000 4
02
#4020
b110010010 3
b110010001 4
12
#4030
b110010011 3
1,
b110010010 4
02
#4040
b110010100 3
b110010011 4
12
#4050
b110010101 3
1-
0,
b110010100 4
02
#4060
b110010110 3
b110010101 4
12
#4070
b110010111 3
1,
b110010110 4
02
#4080
b110011000 3
b110010111 4
12
#4090
b110011001 3
1.
0-
0,
b110011000 4
02
#4100
b110011010 3
b110011001 4
12
#4110
b110011011 3
1,
b110011010 4
02
#4120
b110011100 3
b110011011 4
12
#4130
b110011101 3
1-
0,
b110011100 4
02
#4140
b110011110 3
b110011101 4
12
#4150
b110011111 3
1,
b110011110 4
02
#4160
b110100000 3
b110011111 4
12
#4170
0&
b11111011 5
b110100001 3
10
0/
0.
0-
0,
b110100000 4
02
#4180
1&
b11111111 5
b110100010 3
b110100001 4
12
#4190
0!
b10111111 5
b110100011 3
1,
b110100010 4
02
#4200
1!
b11111111 5
b110100100 3
b110100011 4
12
#4210
0&
b11111011 5
b110100101 3
1-
0,
b110100100 4
02
#4220
1&
b11111111 5
b110100110 3
b110100101 4
12
#4230
0!
b10111111 5
b110100111 3
1,
b110100110 4
02
#4240
1!
b11111111 5
b110101000 3
b110100111 4
12
#4250
b110101001 3
1.
0-
0,
b110101000 4
02
#4260
b110101010 3
b110101001 4
12
#4270
b110101011 3
1,
b110101010 4
02
#4280
b110101100 3
b110101011 4
12
#4290
b110101101 3
1-
0,
b110101100 4
02
#4300
b110101110 3
b110101101 4
12
#4310
b110101111 3
1,
b110101110 4
02
#4320
b110110000 3
b110101111 4
12
#4330
b110110001 3
1/
0.
0-
0,
b110110000 4
02
#4340
b110110010 3
b110110001 4
12
#4350
b110110011 3
1,
b110110010 4
02
#4360
b110110100 3
b110110011 4
12
#4370
b110110101 3
1-
0,
b110110100 4
02
#4380
b110110110 3
b110110101 4
12
#4390
b110110111 3
1,
b110110110 4
02
#4400
b110111000 3
b110110111 4
12
#4410
b110111001 3
1.
0-
0,
b110111000 4
02
#4420
b110111010 3
b110111001 4
12
#4430
b110111011 3
1,
b110111010 4
02
#4440
b110111100 3
b110111011 4
12
#4450
b110111101 3
1-
0,
b110111100 4
02
#4460
b110111110 3
b110111101 4
12
#4470
b110111111 3
1,
b110111110 4
02
#4480
b111000000 3
b110111111 4
12
#4490
b111000001 3
11
00
0/
0.
0-
0,
b111000000 4
02
#4500
b111000010 3
b111000001 4
12
#4510
b111000011 3
1,
b111000010 4
02
#4520
b111000100 3
b111000011 4
12
#4530
b111000101 3
1-
0,
b111000100 4
02
#4540
b111000110 3
b111000101 4
12
#4550
b111000111 3
1,
b111000110 4
02
#4560
b111001000 3
b111000111 4
12
#4570
b111001001 3
1.
0-
0,
b111001000 4
02
#4580
b111001010 3
b111001001 4
12
#4590
b111001011 3
1,
b111001010 4
02
#4600
b111001100 3
b111001011 4
12
#4610
b111001101 3
1-
0,
b111001100 4
02
#4620
b111001110 3
b111001101 4
12
#4630
b111001111 3
1,
b111001110 4
02
#4640
b111010000 3
b111001111 4
12
#4650
0$
b11110111 5
b111010001 3
1/
0.
0-
0,
b111010000 4
02
#4660
1$
b11111111 5
b111010010 3
b111010001 4
12
#4670
0$
b11110111 5
b111010011 3
1,
b111010010 4
02
#4680
1$
b11111111 5
b111010100 3
b111010011 4
12
#4690
0$
b11110111 5
b111010101 3
1-
0,
b111010100 4
02
#4700
1$
b11111111 5
b111010110 3
b111010101 4
12
#4710
0$
b11110111 5
b111010111 3
1,
b111010110 4
02
#4720
1$
b11111111 5
b111011000 3
b111010111 4
12
#4730
b111011001 3
1.
0-
0,
b111011000 4
02
#4740
b111011010 3
b111011001 4
12
#4750
b111011011 3
1,
b111011010 4
02
#4760
b111011100 3
b111011011 4
12
#4770
b111011101 3
1-
0,
b111011100 4
02
#4780
b111011110 3
b111011101 4
12
#4790
b111011111 3
1,
b111011110 4
02
#4800
b111100000 3
b111011111 4
12
#4810
0&
b11111011 5
b111100001 3
10
0/
0.
0-
0,
b111100000 4
02
#4820
1&
b11111111 5
b111100010 3
b111100001 4
12
#4830
0!
b10111111 5
b111100011 3
1,
b111100010 4
02
#4840
1!
b11111111 5
b111100100 3
b111100011 4
12
#4850
0&
b11111011 5
b111100101 3
1-
0,
b111100100 4
02
#4860
1&
b11111111 5
b111100110 3
b111100101 4
12
#4870
0!
b10111111 5
b111100111 3
1,
b111100110 4
02
#4880
1!
b11111111 5
b111101000 3
b111100111 4
12
#4890
b111101001 3
1.
0-
0,
b111101000 4
02
#4900
b111101010 3
b111101001 4
12
#4910
b111101011 3
1,
b111101010 4
02
#4920
b111101100 3
b111101011 4
12
#4930
b111101101 3
1-
0,
b111101100 4
02
#4940
b111101110 3
b111101101 4
12
#4950
b111101111 3
1,
b111101110 4
02
#4960
b111110000 3
b111101111 4
12
#4970
b111110001 3
1/
0.
0-
0,
b111110000 4
02
#4980
b111110010 3
b111110001 4
12
#4990
b111110011 3
1,
b111110010 4
02
#5000
b111110100 3
b111110011 4
12
#5010
0%
b11101111 5
b111110101 3
1-
0,
b111110100 4
02
#5020
b111110110 3
b111110101 4
12
#5030
b111110111 3
1,
b111110110 4
02
#5040
b111111000 3
b111110111 4
12
#5050
1%
b11111111 5
b111111001 3
1.
0-
0,
b111111000 4
02
#5060
b111111010 3
b111111001 4
12
#5070
b111111011 3
1,
b111111010 4
02
