Aliens/verilog/PAL16L8_053327_D20.v
//PAL16L8_053326_D21.v
//Implementation of PAL 053327-D20 combinatorial logic
//used in Aliens Konami Arcade PCB.
//Converted to Verilog By RndMnkIII. 10/2019. (@RndMnkIII).
//---------------------------------------------------------
//Dumped from an unsecured PAL16L8, 
//converted to GAL16V8 with PALTOGAL 
//and tested by Caius (@Caius63417737).
//---------------------------------------------------------
`timescale 1ns / 1ns
module PAL16L8_053327_D20(in, out);
	input [11:0] in;
	output [4:0] out;
	//wire o14, o15;
	reg r14, r15;
	
	always @(in[4] or in[5] or in[6] or in[8] or in[10])
	begin
	    #5  r14 = ~(in[4] & in[5] & in[6] & ~in[8] & ~in[10]);
	end
	
	always @(in[0] or in[2] or in[3] or in[4] or in[5] or in[6] or in[8] or in[9] or in[11])
	begin
	   #5 r15 = ~((~in[0] & ~in[2] & ~in[3] & ~in[4] & ~in[5] & ~in[6] & ~in[8] & ~in[9] & ~in[11]) | (~in[0] & ~in[2] & in[3] & ~in[11]));
	end 
	
	//assign o14 = ~(in[4] & in[5] & in[6] & ~in[8] & ~in[10]);
	
	//assign o15 = ~(~in[0] & ~in[2] & ~in[3] & ~in[4] & ~in[5] & ~in[6] & ~in[8] & ~in[9] & ~in[11] + ~in[0] & ~in[2] & in[3] & ~in[11]);
	
	//assign out[0] = ~(~in[0] & ~in[2] & ~in[3] & ~in[4] & ~in[5] & ~in[6] & ~in[8] & ~in[9] + ~in[0] & ~in[2] & in[3]  + ~in[0] & ~in[1] & ~o14 & ~o15);
	assign #5 out[0] = ~((~in[0] & ~in[2] & ~in[3] & ~in[4] & ~in[5] & ~in[6] & ~in[8] & ~in[9]) | (~in[0] & ~in[2] & in[3])  | (~in[0] & ~in[1] & ~r14 & ~r15));
	//assign out[1] = o14;
	assign out[1] = r14;
	   
	assign #5 out[2] = ~(~in[0] & ~in[7]);

	//assign out[3]  = ~(~in[0] & ~in[1] & in[7] & ~o14 & ~o15);
	assign #5 out[3]  = ~(~in[0] & ~in[1] & in[7] & ~r14 & ~r15);

	assign #5 out[4]  = ~((~in[0] & ~in[2] & ~in[3] & ~in[4] & ~in[5] & ~in[6] & ~in[8] & ~in[9] & ~in[11]) | (~in[0] & ~in[2] & in[3]));
endmodule

Aliens/verilog/PAL16L8_053327_D20_TEST.v
//PAL16L8_053327_D20_TEST.v
//PAL 053327-D20 Testbench.
//used in Aliens Konami Arcade PCB.
//Author: RndMnkIII. 10/2019. (@RndMnkIII).
//---------------------------------------------------------
//iverilog -o pald20_sim PAL16L8_053327_D20.v PAL16L8_053327_D20_TEST.v
//vvp pald20_sim
//gtkwave PAL16L8_053327_D20_TEST.vcd

`timescale 1ns / 1ns
module PAL16L8_053327_D20_TEST;
  reg [12:0] x;
  reg D18_5, D21_17, RMRD, MAA, MA9, MA8, MA7, D21_12, C20_6, C20_3, D21_15, D21_16;
  wire C20_9, IOCS, CRAMCS, VRAMCS, OBJCS;

  PAL16L8_053327_D20 pald20(.in({D18_5, D21_17, RMRD, MAA, MA9, MA8, MA7, D21_12, C20_6, C20_3, D21_15, D21_16}), .out({C20_9, IOCS, CRAMCS, VRAMCS, OBJCS}));
  
  initial
    begin
	  $dumpfile ("PAL16L8_053327_D20_TEST.vcd");
	  $dumpvars (0, PAL16L8_053327_D20_TEST); //0 all variables included
	  $monitor ($time,"\nInputs:\nD18_5\tD21_17\tRMRD\tMAA\tMA9\tMA8\tMA7\tD21_12\tC20_6\tC20_3\tD21_15\tD21_16\n-----\t------\t----\t---\t---\t---\t---\t------\t-----\t-----\t------\t------\n%b\t%b\t%b\t%b\t%b\t%b\t%b\t%b\t%b\t%b\t%b\t%b\n\nOutputs:\nC20_9\tIOCS\tCRAMCS\tVRAMCS\tOBJCS\n-----\t----\t------\t------\t-----\n%b\t%b\t%b\t%b\t%b\n\n----------------------------------------------------------------------------\n\n",D18_5, D21_17, RMRD, MAA, MA9, MA8, MA7, D21_12, C20_6, C20_3, D21_15, D21_16, C20_9, IOCS, CRAMCS, VRAMCS, OBJCS);
	  
	for (x=0; x < 4096; x= x+1)
		begin
    //Suponemos un periodo máximo de 1/25MHz
			#40 ; {D18_5, D21_17, RMRD, MAA, MA9, MA8, MA7, D21_12, C20_6, C20_3, D21_15, D21_16} = x[11:0];
		end // end of for loop 
      #40 $finish;
    end
endmodule

Aliens/verilog/PAL16L8_053327_D20_TEST.vcd
$date
	Thu Oct 10 19:20:03 2019
$end
$version
	Icarus Verilog
$end
$timescale
	1ns
$end
$scope module PAL16L8_053327_D20_TEST $end
$var wire 1 ! VRAMCS $end
$var wire 1 " OBJCS $end
$var wire 1 # IOCS $end
$var wire 1 $ CRAMCS $end
$var wire 1 % C20_9 $end
$var reg 1 & C20_3 $end
$var reg 1 ' C20_6 $end
$var reg 1 ( D18_5 $end
$var reg 1 ) D21_12 $end
$var reg 1 * D21_15 $end
$var reg 1 + D21_16 $end
$var reg 1 , D21_17 $end
$var reg 1 - MA7 $end
$var reg 1 . MA8 $end
$var reg 1 / MA9 $end
$var reg 1 0 MAA $end
$var reg 1 1 RMRD $end
$var reg 13 2 x [12:0] $end
$scope module pald20 $end
$var wire 12 3 in [11:0] $end
$var wire 5 4 out [4:0] $end
$var reg 1 5 r14 $end
$var reg 1 6 r15 $end
$upscope $end
$upscope $end
$enddefinitions $end
#0
$dumpvars
x6
x5
bx 4
bx 3
b0 2
x1
x0
x/
x.
x-
x,
x+
x*
x)
x(
x'
x&
x%
x$
x#
x"
x!
$end
#40
b1 2
0(
0,
01
00
0/
0.
0-
0)
0'
0&
0*
b0 3
0+
#45
0"
0%
1#
0$
1!
b1010 4
15
06
#80
b10 2
b1 3
1+
#85
1"
1%
1$
b11111 4
16
#120
b11 2
1*
b10 3
0+
#125
0"
0%
0$
b1010 4
06
#160
b100 2
b11 3
1+
#165
1"
1%
1$
b11111 4
16
#200
b101 2
1&
0*
b100 3
0+
#205
0$
b11011 4
#240
b110 2
b101 3
1+
#245
1$
b11111 4
#280
b111 2
1*
b110 3
0+
#285
0$
b11011 4
#320
b1000 2
b111 3
1+
#325
1$
b11111 4
#360
b1001 2
1'
0&
0*
b1000 3
0+
#365
0"
0%
0$
b1010 4
06
#400
b1010 2
b1001 3
1+
#405
1"
1%
1$
b11111 4
16
#440
b1011 2
1*
b1010 3
0+
#445
0"
0%
0$
b1010 4
06
#480
b1100 2
b1011 3
1+
#485
1"
1%
1$
b11111 4
16
#520
b1101 2
1&
0*
b1100 3
0+
#525
0$
b11011 4
#560
b1110 2
b1101 3
1+
#565
1$
b11111 4
#600
b1111 2
1*
b1110 3
0+
#605
0$
b11011 4
#640
b10000 2
b1111 3
1+
#645
1$
b11111 4
#680
b10001 2
1)
0'
0&
0*
b10000 3
0+
#685
0$
b11011 4
#720
b10010 2
b10001 3
1+
#725
1$
b11111 4
#760
b10011 2
1*
b10010 3
0+
#765
0$
b11011 4
#800
b10100 2
b10011 3
1+
#805
1$
b11111 4
#840
b10101 2
1&
0*
b10100 3
0+
#845
0$
b11011 4
#880
b10110 2
b10101 3
1+
#885
1$
b11111 4
#920
b10111 2
1*
b10110 3
0+
#925
0$
b11011 4
#960
b11000 2
b10111 3
1+
#965
1$
b11111 4
#1000
b11001 2
1'
0&
0*
b11000 3
0+
#1005
0"
0%
0$
b1010 4
06
#1040
b11010 2
b11001 3
1+
#1045
1"
1%
1$
b11111 4
16
#1080
b11011 2
1*
b11010 3
0+
#1085
0"
0%
0$
b1010 4
06
#1120
b11100 2
b11011 3
1+
#1125
1"
1%
1$
b11111 4
16
#1160
b11101 2
1&
0*
b11100 3
0+
#1165
0$
b11011 4
#1200
b11110 2
b11101 3
1+
#1205
1$
b11111 4
#1240
b11111 2
1*
b11110 3
0+
#1245
0$
b11011 4
#1280
b100000 2
b11111 3
1+
#1285
1$
b11111 4
#1320
b100001 2
1-
0)
0'
0&
0*
b100000 3
0+
#1325
0$
b11011 4
#1360
b100010 2
b100001 3
1+
#1365
1$
b11111 4
#1400
b100011 2
1*
b100010 3
0+
#1405
0$
b11011 4
#1440
b100100 2
b100011 3
1+
#1445
1$
b11111 4
#1480
b100101 2
1&
0*
b100100 3
0+
#1485
0$
b11011 4
#1520
b100110 2
b100101 3
1+
#1525
1$
b11111 4
#1560
b100111 2
1*
b100110 3
0+
#1565
0$
b11011 4
#1600
b101000 2
b100111 3
1+
#1605
1$
b11111 4
#1640
b101001 2
1'
0&
0*
b101000 3
0+
#1645
0"
0%
0$
b1010 4
06
#1680
b101010 2
b101001 3
1+
#1685
1"
1%
1$
b11111 4
16
#1720
b101011 2
1*
b101010 3
0+
#1725
0"
0%
0$
b1010 4
06
#1760
b101100 2
b101011 3
1+
#1765
1"
1%
1$
b11111 4
16
#1800
b101101 2
1&
0*
b101100 3
0+
#1805
0$
b11011 4
#1840
b101110 2
b101101 3
1+
#1845
1$
b11111 4
#1880
b101111 2
1*
b101110 3
0+
#1885
0$
b11011 4
#1920
b110000 2
b101111 3
1+
#1925
1$
b11111 4
#1960
b110001 2
1)
0'
0&
0*
b110000 3
0+
#1965
0$
b11011 4
#2000
b110010 2
b110001 3
1+
#2005
1$
b11111 4
#2040
b110011 2
1*
b110010 3
0+
#2045
0$
b11011 4
#2080
b110100 2
b110011 3
1+
#2085
1$
b11111 4
#2120
b110101 2
1&
0*
b110100 3
0+
#2125
0$
b11011 4
#2160
b110110 2
b110101 3
1+
#2165
1$
b11111 4
#2200
b110111 2
1*
b110110 3
0+
#2205
0$
b11011 4
#2240
b111000 2
b110111 3
1+
#2245
1$
b11111 4
#2280
b111001 2
1'
0&
0*
b111000 3
0+
#2285
0"
0%
0$
b1010 4
06
#2320
b111010 2
b111001 3
1+
#2325
1"
1%
1$
b11111 4
16
#2360
b111011 2
1*
b111010 3
0+
#2365
0"
0%
0$
b1010 4
06
#2400
b111100 2
b111011 3
1+
#2405
1"
1%
1$
b11111 4
16
#2440
b111101 2
1&
0*
b111100 3
0+
#2445
0$
b11011 4
#2480
b111110 2
b111101 3
1+
#2485
1$
b11111 4
#2520
b111111 2
1*
b111110 3
0+
#2525
0$
b11011 4
#2560
b1000000 2
b111111 3
1+
#2565
1$
b11111 4
#2600
b1000001 2
1.
0-
0)
0'
0&
0*
b1000000 3
0+
#2605
0$
b11011 4
#2640
b1000010 2
b1000001 3
1+
#2645
1$
b11111 4
#2680
b1000011 2
1*
b1000010 3
0+
#2685
0$
b11011 4
#2720
b1000100 2
b1000011 3
1+
#2725
1$
b11111 4
#2760
b1000101 2
1&
0*
b1000100 3
0+
#2765
0$
b11011 4
#2800
b1000110 2
b1000101 3
1+
#2805
1$
b11111 4
#2840
b1000111 2
1*
b1000110 3
0+
#2845
0$
b11011 4
#2880
b1001000 2
b1000111 3
1+
#2885
1$
b11111 4
#2920
b1001001 2
1'
0&
0*
b1001000 3
0+
#2925
0"
0%
0$
b1010 4
06
#2960
b1001010 2
b1001001 3
1+
#2965
1"
1%
1$
b11111 4
16
#3000
b1001011 2
1*
b1001010 3
0+
#3005
0"
0%
0$
b1010 4
06
#3040
b1001100 2
b1001011 3
1+
#3045
1"
1%
1$
b11111 4
16
#3080
b1001101 2
1&
0*
b1001100 3
0+
#3085
0$
b11011 4
#3120
b1001110 2
b1001101 3
1+
#3125
1$
b11111 4
#3160
b1001111 2
1*
b1001110 3
0+
#3165
0$
b11011 4
#3200
b1010000 2
b1001111 3
1+
#3205
1$
b11111 4
#3240
b1010001 2
1)
0'
0&
0*
b1010000 3
0+
#3245
0$
b11011 4
#3280
b1010010 2
b1010001 3
1+
#3285
1$
b11111 4
#3320
b1010011 2
1*
b1010010 3
0+
#3325
0$
b11011 4
#3360
b1010100 2
b1010011 3
1+
#3365
1$
b11111 4
#3400
b1010101 2
1&
0*
b1010100 3
0+
#3405
0$
b11011 4
#3440
b1010110 2
b1010101 3
1+
#3445
1$
b11111 4
#3480
b1010111 2
1*
b1010110 3
0+
#3485
0$
b11011 4
#3520
b1011000 2
b1010111 3
1+
#3525
1$
b11111 4
#3560
b1011001 2
1'
0&
0*
b1011000 3
0+
#3565
0"
0%
0$
b1010 4
06
#3600
b1011010 2
b1011001 3
1+
#3605
1"
1%
1$
b11111 4
16
#3640
b1011011 2
1*
b1011010 3
0+
#3645
0"
0%
0$
b1010 4
06
#3680
b1011100 2
b1011011 3
1+
#3685
1"
1%
1$
b11111 4
16
#3720
b1011101 2
1&
0*
b1011100 3
0+
#3725
0$
b11011 4
#3760
b1011110 2
b1011101 3
1+
#3765
1$
b11111 4
#3800
b1011111 2
1*
b1011110 3
0+
#3805
0$
b11011 4
#3840
b1100000 2
b1011111 3
1+
#3845
1$
b11111 4
#3880
b1100001 2
1-
0)
0'
0&
0*
b1100000 3
0+
#3885
0$
b11011 4
#3920
b1100010 2
b1100001 3
1+
#3925
1$
b11111 4
#3960
b1100011 2
1*
b1100010 3
0+
#3965
0$
b11011 4
#4000
b1100100 2
b1100011 3
1+
#4005
1$
b11111 4
#4040
b1100101 2
1&
0*
b1100100 3
0+
#4045
0$
b11011 4
#4080
b1100110 2
b1100101 3
1+
#4085
1$
b11111 4
#4120
b1100111 2
1*
b1100110 3
0+
#4125
0$
b11011 4
#4160
b1101000 2
b1100111 3
1+
#4165
1$
b11111 4
#4200
b1101001 2
1'
0&
0*
b1101000 3
0+
#4205
0"
0%
0$
b1010 4
06
#4240
b1101010 2
b1101001 3
1+
#4245
1"
1%
1$
b11111 4
16
#4280
b1101011 2
1*
b1101010 3
0+
#4285
0"
0%
0$
b1010 4
06
#4320
b1101100 2
b1101011 3
1+
#4325
1"
1%
1$
b11111 4
16
#4360
b1101101 2
1&
0*
b1101100 3
0+
#4365
0$
b11011 4
#4400
b1101110 2
b1101101 3
1+
#4405
1$
b11111 4
#4440
b1101111 2
1*
b1101110 3
0+
#4445
0$
b11011 4
#4480
b1110000 2
b1101111 3
1+
#4485
1$
b11111 4
#4520
b1110001 2
1)
0'
0&
0*
b1110000 3
0+
#4525
0$
0!
b11001 4
05
#4560
b1110010 2
b1110001 3
1+
#4565
1$
b11101 4
#4600
b1110011 2
1*
b1110010 3
0+
#4605
0$
b11001 4
#4640
b1110100 2
b1110011 3
1+
#4645
1$
b11101 4
#4680
b1110101 2
1&
0*
b1110100 3
0+
#4685
0$
b11001 4
#4720
b1110110 2
b1110101 3
1+
#4725
1$
b11101 4
#4760
b1110111 2
1*
b1110110 3
0+
#4765
0$
b11001 4
#4800
b1111000 2
b1110111 3
1+
#4805
1$
b11101 4
#4840
b1111001 2
1'
0&
0*
b1111000 3
0+
#4845
0"
0%
0$
b1000 4
06
#4880
b1111010 2
b1111001 3
1+
#4885
1"
1%
1$
b11101 4
16
#4920
b1111011 2
1*
b1111010 3
0+
#4925
0"
0%
0$
b1000 4
06
#4960
b1111100 2
b1111011 3
1+
#4965
1"
1%
1$
b11101 4
16
#5000
b1111101 2
1&
0*
b1111100 3
0+
#5005
0$
b11001 4
#5040
b1111110 2
b1111101 3
1+
#5045
1$
b11101 4
#5080
b1111111 2
1*
b1111110 3
0+
#5085
0$
b11001 4
#5120
b10000000 2
b1111111 3
1+
#5125
1$
b11101 4
#5160
b10000001 2
1/
0.
0-
0)
0'
0&
0*
b10000000 3
0+
#5165
0"
0%
1!
b1110 4
15
06
#5200
b10000010 2
b10000001 3
1+
#5205
1"
1%
b11111 4
16
#5240
b10000011 2
1*
b10000010 3
0+
#5245
0"
0%
b1110 4
06
#5280
b10000100 2
b10000011 3
1+
#5285
1"
1%
b11111 4
16
#5320
b10000101 2
1&
0*
b10000100 3
0+
#5360
b10000110 2
b10000101 3
1+
#5400
b10000111 2
1*
b10000110 3
0+
#5440
b10001000 2
b10000111 3
1+
#5480
b10001001 2
1'
0&
0*
b10001000 3
0+
#5485
0"
0%
b1110 4
06
#5520
b10001010 2
b10001001 3
1+
#5525
1"
1%
b11111 4
16
#5560
b10001011 2
1*
b10001010 3
0+
#5565
0"
0%
b1110 4
06
#5600
b10001100 2
b10001011 3
1+
#5605
1"
1%
b11111 4
16
#5640
b10001101 2
1&
0*
b10001100 3
0+
#5680
b10001110 2
b10001101 3
1+
#5720
b10001111 2
1*
b10001110 3
0+
#5760
b10010000 2
b10001111 3
1+
#5800
b10010001 2
1)
0'
0&
0*
b10010000 3
0+
#5840
b10010010 2
b10010001 3
1+
#5880
b10010011 2
1*
b10010010 3
0+
#5920
b10010100 2
b10010011 3
1+
#5960
b10010101 2
1&
0*
b10010100 3
0+
#6000
b10010110 2
b10010101 3
1+
#6040
b10010111 2
1*
b10010110 3
0+
#6080
b10011000 2
b10010111 3
1+
#6120
b10011001 2
1'
0&
0*
b10011000 3
0+
#6125
0"
0%
b1110 4
06
#6160
b10011010 2
b10011001 3
1+
#6165
1"
1%
b11111 4
16
#6200
b10011011 2
1*
b10011010 3
0+
#6205
0"
0%
b1110 4
06
#6240
b10011100 2
b10011011 3
1+
#6245
1"
1%
b11111 4
16
#6280
b10011101 2
1&
0*
b10011100 3
0+
#6320
b10011110 2
b10011101 3
1+
#6360
b10011111 2
1*
b10011110 3
0+
#6400
b10100000 2
b10011111 3
1+
#6440
b10100001 2
1-
0)
0'
0&
0*
b10100000 3
0+
#6480
b10100010 2
b10100001 3
1+
#6520
b10100011 2
1*
b10100010 3
0+
#6560
b10100100 2
b10100011 3
1+
#6600
b10100101 2
1&
0*
b10100100 3
0+
#6640
b10100110 2
b10100101 3
1+
#6680
b10100111 2
1*
b10100110 3
0+
#6720
b10101000 2
b10100111 3
1+
#6760
b10101001 2
1'
0&
0*
b10101000 3
0+
#6765
0"
0%
b1110 4
06
#6800
b10101010 2
b10101001 3
1+
#6805
1"
1%
b11111 4
16
#6840
b10101011 2
1*
b10101010 3
0+
#6845
0"
0%
b1110 4
06
#6880
b10101100 2
b10101011 3
1+
#6885
1"
1%
b11111 4
16
#6920
b10101101 2
1&
0*
b10101100 3
0+
#6960
b10101110 2
b10101101 3
1+
#7000
b10101111 2
1*
b10101110 3
0+
#7040
b10110000 2
b10101111 3
1+
#7080
b10110001 2
1)
0'
0&
0*
b10110000 3
0+
#7120
b10110010 2
b10110001 3
1+
#7160
b10110011 2
1*
b10110010 3
0+
#7200
b10110100 2
b10110011 3
1+
#7240
b10110101 2
1&
0*
b10110100 3
0+
#7280
b10110110 2
b10110101 3
1+
#7320
b10110111 2
1*
b10110110 3
0+
#7360
b10111000 2
b10110111 3
1+
#7400
b10111001 2
1'
0&
0*
b10111000 3
0+
#7405
0"
0%
b1110 4
06
#7440
b10111010 2
b10111001 3
1+
#7445
1"
1%
b11111 4
16
#7480
b10111011 2
1*
b10111010 3
0+
#7485
0"
0%
b1110 4
06
#7520
b10111100 2
b10111011 3
1+
#7525
1"
1%
b11111 4
16
#7560
b10111101 2
1&
0*
b10111100 3
0+
#7600
b10111110 2
b10111101 3
1+
#7640
b10111111 2
1*
b10111110 3
0+
#7680
b11000000 2
b10111111 3
1+
#7720
b11000001 2
1.
0-
0)
0'
0&
0*
b11000000 3
0+
#7760
b11000010 2
b11000001 3
1+
#7800
b11000011 2
1*
b11000010 3
0+
#7840
b11000100 2
b11000011 3
1+
#7880
b11000101 2
1&
0*
b11000100 3
0+
#7920
b11000110 2
b11000101 3
1+
#7960
b11000111 2
1*
b11000110 3
0+
#8000
b11001000 2
b11000111 3
1+
#8040
b11001001 2
1'
0&
0*
b11001000 3
0+
#8045
0"
0%
b1110 4
06
#8080
b11001010 2
b11001001 3
1+
#8085
1"
1%
b11111 4
16
#8120
b11001011 2
1*
b11001010 3
0+
#8125
0"
0%
b1110 4
06
#8160
b11001100 2
b11001011 3
1+
#8165
1"
1%
b11111 4
16
#8200
b11001101 2
1&
0*
b11001100 3
0+
#8240
b11001110 2
b11001101 3
1+
#8280
b11001111 2
1*
b11001110 3
0+
#8320
b11010000 2
b11001111 3
1+
#8360
b11010001 2
1)
0'
0&
0*
b11010000 3
0+
#8400
b11010010 2
b11010001 3
1+
#8440
b11010011 2
1*
b11010010 3
0+
#8480
b11010100 2
b11010011 3
1+
#8520
b11010101 2
1&
0*
b11010100 3
0+
#8560
b11010110 2
b11010101 3
1+
#8600
b11010111 2
1*
b11010110 3
0+
#8640
b11011000 2
b11010111 3
1+
#8680
b11011001 2
1'
0&
0*
b11011000 3
0+
#8685
0"
0%
b1110 4
06
#8720
b11011010 2
b11011001 3
1+
#8725
1"
1%
b11111 4
16
#8760
b11011011 2
1*
b11011010 3
0+
#8765
0"
0%
b1110 4
06
#8800
b11011100 2
b11011011 3
1+
#8805
1"
1%
b11111 4
16
#8840
b11011101 2
1&
0*
b11011100 3
0+
#8880
b11011110 2
b11011101 3
1+
#8920
b11011111 2
1*
b11011110 3
0+
#8960
b11100000 2
b11011111 3
1+
#9000
b11100001 2
1-
0)
0'
0&
0*
b11100000 3
0+
#9040
b11100010 2
b11100001 3
1+
#9080
b11100011 2
1*
b11100010 3
0+
#9120
b11100100 2
b11100011 3
1+
#9160
b11100101 2
1&
0*
b11100100 3
0+
#9200
b11100110 2
b11100101 3
1+
#9240
b11100111 2
1*
b11100110 3
0+
#9280
b11101000 2
b11100111 3
1+
#9320
b11101001 2
1'
0&
0*
b11101000 3
0+
#9325
0"
0%
b1110 4
06
#9360
b11101010 2
b11101001 3
1+
#9365
1"
1%
b11111 4
16
#9400
b11101011 2
1*
b11101010 3
0+
#9405
0"
0%
b1110 4
06
#9440
b11101100 2
b11101011 3
1+
#9445
1"
1%
b11111 4
16
#9480
b11101101 2
1&
0*
b11101100 3
0+
#9520
b11101110 2
b11101101 3
1+
#9560
b11101111 2
1*
b11101110 3
0+
#9600
b11110000 2
b11101111 3
1+
#9640
b11110001 2
1)
0'
0&
0*
b11110000 3
0+
#9645
0!
b11101 4
05
#9680
b11110010 2
b11110001 3
1+
#9720
b11110011 2
1*
b11110010 3
0+
#9760
b11110100 2
b11110011 3
1+
#9800
b11110101 2
1&
0*
b11110100 3
0+
#9840
b11110110 2
b11110101 3
1+
#9880
b11110111 2
1*
b11110110 3
0+
#9920
b11111000 2
b11110111 3
1+
#9960
b11111001 2
1'
0&
0*
b11111000 3
0+
#9965
0"
0%
b1100 4
06
#9970
0#
b100 4
#10000
b11111010 2
b11111001 3
1+
#10005
1"
1#
1%
b11101 4
16
#10040
b11111011 2
1*
b11111010 3
0+
#10045
0"
0%
b1100 4
06
#10080
b11111100 2
b11111011 3
1+
#10085
1"
1%
b11101 4
16
#10120
b11111101 2
1&
0*
b11111100 3
0+
#10160
b11111110 2
b11111101 3
1+
#10200
b11111111 2
1*
b11111110 3
0+
#10240
b100000000 2
b11111111 3
1+
#10280
b100000001 2
10
0/
0.
0-
0)
0'
0&
0*
b100000000 3
0+
#10285
0$
1!
b11011 4
15
#10320
b100000010 2
b100000001 3
1+
#10325
1$
b11111 4
#10360
b100000011 2
1*
b100000010 3
0+
#10365
0$
b11011 4
#10400
b100000100 2
b100000011 3
1+
#10405
1$
b11111 4
#10440
b100000101 2
1&
0*
b100000100 3
0+
#10445
0$
b11011 4
#10480
b100000110 2
b100000101 3
1+
#10485
1$
b11111 4
#10520
b100000111 2
1*
b100000110 3
0+
#10525
0$
b11011 4
#10560
b100001000 2
b100000111 3
1+
#10565
1$
b11111 4
#10600
b100001001 2
1'
0&
0*
b100001000 3
0+
#10605
0"
0%
0$
b1010 4
06
#10640
b100001010 2
b100001001 3
1+
#10645
1"
1%
1$
b11111 4
16
#10680
b100001011 2
1*
b100001010 3
0+
#10685
0"
0%
0$
b1010 4
06
#10720
b100001100 2
b100001011 3
1+
#10725
1"
1%
1$
b11111 4
16
#10760
b100001101 2
1&
0*
b100001100 3
0+
#10765
0$
b11011 4
#10800
b100001110 2
b100001101 3
1+
#10805
1$
b11111 4
#10840
b100001111 2
1*
b100001110 3
0+
#10845
0$
b11011 4
#10880
b100010000 2
b100001111 3
1+
#10885
1$
b11111 4
#10920
b100010001 2
1)
0'
0&
0*
b100010000 3
0+
#10925
0$
b11011 4
#10960
b100010010 2
b100010001 3
1+
#10965
1$
b11111 4
#11000
b100010011 2
1*
b100010010 3
0+
#11005
0$
b11011 4
#11040
b100010100 2
b100010011 3
1+
#11045
1$
b11111 4
#11080
b100010101 2
1&
0*
b100010100 3
0+
#11085
0$
b11011 4
#11120
b100010110 2
b100010101 3
1+
#11125
1$
b11111 4
#11160
b100010111 2
1*
b100010110 3
0+
#11165
0$
b11011 4
#11200
b100011000 2
b100010111 3
1+
#11205
1$
b11111 4
#11240
b100011001 2
1'
0&
0*
b100011000 3
0+
#11245
0"
0%
0$
b1010 4
06
#11280
b100011010 2
b100011001 3
1+
#11285
1"
1%
1$
b11111 4
16
#11320
b100011011 2
1*
b100011010 3
0+
#11325
0"
0%
0$
b1010 4
06
#11360
b100011100 2
b100011011 3
1+
#11365
1"
1%
1$
b11111 4
16
#11400
b100011101 2
1&
0*
b100011100 3
0+
#11405
0$
b11011 4
#11440
b100011110 2
b100011101 3
1+
#11445
1$
b11111 4
#11480
b100011111 2
1*
b100011110 3
0+
#11485
0$
b11011 4
#11520
b100100000 2
b100011111 3
1+
#11525
1$
b11111 4
#11560
b100100001 2
1-
0)
0'
0&
0*
b100100000 3
0+
#11565
0$
b11011 4
#11600
b100100010 2
b100100001 3
1+
#11605
1$
b11111 4
#11640
b100100011 2
1*
b100100010 3
0+
#11645
0$
b11011 4
#11680
b100100100 2
b100100011 3
1+
#11685
1$
b11111 4
#11720
b100100101 2
1&
0*
b100100100 3
0+
#11725
0$
b11011 4
#11760
b100100110 2
b100100101 3
1+
#11765
1$
b11111 4
#11800
b100100111 2
1*
b100100110 3
0+
#11805
0$
b11011 4
#11840
b100101000 2
b100100111 3
1+
#11845
1$
b11111 4
#11880
b100101001 2
1'
0&
0*
b100101000 3
0+
#11885
0"
0%
0$
b1010 4
06
#11920
b100101010 2
b100101001 3
1+
#11925
1"
1%
1$
b11111 4
16
#11960
b100101011 2
1*
b100101010 3
0+
#11965
0"
0%
0$
b1010 4
06
#12000
b100101100 2
b100101011 3
1+
#12005
1"
1%
1$
b11111 4
16
#12040
b100101101 2
1&
0*
b100101100 3
0+
#12045
0$
b11011 4
#12080
b100101110 2
b100101101 3
1+
#12085
1$
b11111 4
#12120
b100101111 2
1*
b100101110 3
0+
#12125
0$
b11011 4
#12160
b100110000 2
b100101111 3
1+
#12165
1$
b11111 4
#12200
b100110001 2
1)
0'
0&
0*
b100110000 3
0+
#12205
0$
b11011 4
#12240
b100110010 2
b100110001 3
1+
#12245
1$
b11111 4
#12280
b100110011 2
1*
b100110010 3
0+
#12285
0$
b11011 4
#12320
b100110100 2
b100110011 3
1+
#12325
1$
b11111 4
#12360
b100110101 2
1&
0*
b100110100 3
0+
#12365
0$
b11011 4
#12400
b100110110 2
b100110101 3
1+
#12405
1$
b11111 4
#12440
b100110111 2
1*
b100110110 3
0+
#12445
0$
b11011 4
#12480
b100111000 2
b100110111 3
1+
#12485
1$
b11111 4
#12520
b100111001 2
1'
0&
0*
b100111000 3
0+
#12525
0"
0%
0$
b1010 4
06
#12560
b100111010 2
b100111001 3
1+
#12565
1"
1%
1$
b11111 4
16
#12600
b100111011 2
1*
b100111010 3
0+
#12605
0"
0%
0$
b1010 4
06
#12640
b100111100 2
b100111011 3
1+
#12645
1"
1%
1$
b11111 4
16
#12680
b100111101 2
1&
0*
b100111100 3
0+
#12685
0$
b11011 4
#12720
b100111110 2
b100111101 3
1+
#12725
1$
b11111 4
#12760
b100111111 2
1*
b100111110 3
0+
#12765
0$
b11011 4
#12800
b101000000 2
b100111111 3
1+
#12805
1$
b11111 4
#12840
b101000001 2
1.
0-
0)
0'
0&
0*
b101000000 3
0+
#12845
0$
b11011 4
#12880
b101000010 2
b101000001 3
1+
#12885
1$
b11111 4
#12920
b101000011 2
1*
b101000010 3
0+
#12925
0$
b11011 4
#12960
b101000100 2
b101000011 3
1+
#12965
1$
b11111 4
#13000
b101000101 2
1&
0*
b101000100 3
0+
#13005
0$
b11011 4
#13040
b101000110 2
b101000101 3
1+
#13045
1$
b11111 4
#13080
b101000111 2
1*
b101000110 3
0+
#13085
0$
b11011 4
#13120
b101001000 2
b101000111 3
1+
#13125
1$
b11111 4
#13160
b101001001 2
1'
0&
0*
b101001000 3
0+
#13165
0"
0%
0$
b1010 4
06
#13200
b101001010 2
b101001001 3
1+
#13205
1"
1%
1$
b11111 4
16
#13240
b101001011 2
1*
b101001010 3
0+
#13245
0"
0%
0$
b1010 4
06
#13280
b101001100 2
b101001011 3
1+
#13285
1"
1%
1$
b11111 4
16
#13320
b101001101 2
1&
0*
b101001100 3
0+
#13325
0$
b11011 4
#13360
b101001110 2
b101001101 3
1+
#13365
1$
b11111 4
#13400
b101001111 2
1*
b101001110 3
0+
#13405
0$
b11011 4
#13440
b101010000 2
b101001111 3
1+
#13445
1$
b11111 4
#13480
b101010001 2
1)
0'
0&
0*
b101010000 3
0+
#13485
0$
b11011 4
#13520
b101010010 2
b101010001 3
1+
#13525
1$
b11111 4
#13560
b101010011 2
1*
b101010010 3
0+
#13565
0$
b11011 4
#13600
b101010100 2
b101010011 3
1+
#13605
1$
b11111 4
#13640
b101010101 2
1&
0*
b101010100 3
0+
#13645
0$
b11011 4
#13680
b101010110 2
b101010101 3
1+
#13685
1$
b11111 4
#13720
b101010111 2
1*
b101010110 3
0+
#13725
0$
b11011 4
#13760
b101011000 2
b101010111 3
1+
#13765
1$
b11111 4
#13800
b101011001 2
1'
0&
0*
b101011000 3
0+
#13805
0"
0%
0$
b1010 4
06
#13840
b101011010 2
b101011001 3
1+
#13845
1"
1%
1$
b11111 4
16
#13880
b101011011 2
1*
b101011010 3
0+
#13885
0"
0%
0$
b1010 4
06
#13920
b101011100 2
b101011011 3
1+
#13925
1"
1%
1$
b11111 4
16
